<?xml version="1.0" encoding="utf-8"?>
<MapData>
<Details>
<FileName>[mythrimine_hide]000.rmd</FileName>
<FileType>Red Stone Scenario File 6.9 beta</FileType>
<MapName>ミスリル鉱山の隠された鉄鉱</MapName>
<SysWidth>110</SysWidth>
<SysHeight>110</SysHeight>
<TgaWidth>400</TgaWidth>
<TgaHeight>200</TgaHeight>
<MapType>1</MapType>
<isPremiumMap>0</isPremiumMap>
<isPvPMap>0</isPvPMap>
<MapView_Lv>1</MapView_Lv>
<isLocationStrage>0</isLocationStrage>
<P_SubElement1>0</P_SubElement1>
<P_SubElement2>0</P_SubElement2>
<P_SubElement3>0</P_SubElement3>
<P_SubElement4>0</P_SubElement4>
<P_SubElement5>0</P_SubElement5>
<P_SubElement6>0</P_SubElement6>
<M_AddElement1>0</M_AddElement1>
<M_AddElement2>0</M_AddElement2>
<M_AddElement3>0</M_AddElement3>
<M_AddElement4>0</M_AddElement4>
<M_AddElement5>0</M_AddElement5>
<M_AddElement6>0</M_AddElement6>
</Details>
<CharacterData>
<Character id="cUid0">
<CharacterUID>0</CharacterUID>
<CharacterName>マーブルガゴイル</CharacterName>
<CharacterType>2</CharacterType>
<InternalID>0</InternalID>
<PopSpeed>120</PopSpeed>
<isPTBoss>0</isPTBoss>
<PopPoint_X>149.26</PopPoint_X>
<PopPoint_Y>66.36</PopPoint_Y>
</Character>
<Character id="cUid1">
<CharacterUID>1</CharacterUID>
<CharacterName>トラウス</CharacterName>
<CharacterType>1</CharacterType>
<InternalID>13</InternalID>
<PopSpeed>120</PopSpeed>
<isPTBoss>0</isPTBoss>
<PopPoint_X>197.44</PopPoint_X>
<PopPoint_Y>87.33</PopPoint_Y>
</Character>
<Character id="cUid3">
<CharacterUID>3</CharacterUID>
<CharacterName>鷲狂戦士</CharacterName>
<CharacterType>2</CharacterType>
<InternalID>7</InternalID>
<PopSpeed>120</PopSpeed>
<isPTBoss>0</isPTBoss>
<PopPoint_X>209.15</PopPoint_X>
<PopPoint_Y>50.74</PopPoint_Y>
</Character>
<Character id="cUid4">
<CharacterUID>4</CharacterUID>
<CharacterName>鷲狂戦士</CharacterName>
<CharacterType>2</CharacterType>
<InternalID>7</InternalID>
<PopSpeed>120</PopSpeed>
<isPTBoss>0</isPTBoss>
<PopPoint_X>198.69</PopPoint_X>
<PopPoint_Y>57.10</PopPoint_Y>
</Character>
<Character id="cUid5">
<CharacterUID>5</CharacterUID>
<CharacterName>鷲狂戦士</CharacterName>
<CharacterType>2</CharacterType>
<InternalID>7</InternalID>
<PopSpeed>120</PopSpeed>
<isPTBoss>0</isPTBoss>
<PopPoint_X>214.55</PopPoint_X>
<PopPoint_Y>70.68</PopPoint_Y>
</Character>
<Character id="cUid6">
<CharacterUID>6</CharacterUID>
<CharacterName>鷲狂戦士</CharacterName>
<CharacterType>2</CharacterType>
<InternalID>7</InternalID>
<PopSpeed>120</PopSpeed>
<isPTBoss>0</isPTBoss>
<PopPoint_X>221.08</PopPoint_X>
<PopPoint_Y>78.92</PopPoint_Y>
</Character>
<Character id="cUid7">
<CharacterUID>7</CharacterUID>
<CharacterName>マーブルガゴイル</CharacterName>
<CharacterType>2</CharacterType>
<InternalID>0</InternalID>
<PopSpeed>120</PopSpeed>
<isPTBoss>0</isPTBoss>
<PopPoint_X>142.44</PopPoint_X>
<PopPoint_Y>59.43</PopPoint_Y>
</Character>
<Character id="cUid8">
<CharacterUID>8</CharacterUID>
<CharacterName>マーブルガゴイル</CharacterName>
<CharacterType>2</CharacterType>
<InternalID>0</InternalID>
<PopSpeed>120</PopSpeed>
<isPTBoss>0</isPTBoss>
<PopPoint_X>141.31</PopPoint_X>
<PopPoint_Y>69.15</PopPoint_Y>
</Character>
<Character id="cUid10">
<CharacterUID>10</CharacterUID>
<CharacterName>マゴット</CharacterName>
<CharacterType>2</CharacterType>
<InternalID>1</InternalID>
<PopSpeed>120</PopSpeed>
<isPTBoss>0</isPTBoss>
<PopPoint_X>105.45</PopPoint_X>
<PopPoint_Y>45.91</PopPoint_Y>
</Character>
<Character id="cUid12">
<CharacterUID>12</CharacterUID>
<CharacterName>マゴット</CharacterName>
<CharacterType>2</CharacterType>
<InternalID>1</InternalID>
<PopSpeed>120</PopSpeed>
<isPTBoss>0</isPTBoss>
<PopPoint_X>105.85</PopPoint_X>
<PopPoint_Y>58.69</PopPoint_Y>
</Character>
<Character id="cUid13">
<CharacterUID>13</CharacterUID>
<CharacterName>オーガ</CharacterName>
<CharacterType>2</CharacterType>
<InternalID>8</InternalID>
<PopSpeed>120</PopSpeed>
<isPTBoss>0</isPTBoss>
<PopPoint_X>107.22</PopPoint_X>
<PopPoint_Y>52.33</PopPoint_Y>
</Character>
<Character id="cUid14">
<CharacterUID>14</CharacterUID>
<CharacterName>マゴット</CharacterName>
<CharacterType>2</CharacterType>
<InternalID>1</InternalID>
<PopSpeed>120</PopSpeed>
<isPTBoss>0</isPTBoss>
<PopPoint_X>118.58</PopPoint_X>
<PopPoint_Y>133.07</PopPoint_Y>
</Character>
<Character id="cUid15">
<CharacterUID>15</CharacterUID>
<CharacterName>マゴット</CharacterName>
<CharacterType>2</CharacterType>
<InternalID>1</InternalID>
<PopSpeed>120</PopSpeed>
<isPTBoss>0</isPTBoss>
<PopPoint_X>128.30</PopPoint_X>
<PopPoint_Y>133.24</PopPoint_Y>
</Character>
<Character id="cUid18">
<CharacterUID>18</CharacterUID>
<CharacterName>オーガ</CharacterName>
<CharacterType>2</CharacterType>
<InternalID>8</InternalID>
<PopSpeed>120</PopSpeed>
<isPTBoss>0</isPTBoss>
<PopPoint_X>126.14</PopPoint_X>
<PopPoint_Y>152.33</PopPoint_Y>
</Character>
<Character id="cUid19">
<CharacterUID>19</CharacterUID>
<CharacterName>オーガ</CharacterName>
<CharacterType>2</CharacterType>
<InternalID>8</InternalID>
<PopSpeed>120</PopSpeed>
<isPTBoss>0</isPTBoss>
<PopPoint_X>235.74</PopPoint_X>
<PopPoint_Y>118.58</PopPoint_Y>
</Character>
<Character id="cUid20">
<CharacterUID>20</CharacterUID>
<CharacterName>オーガ</CharacterName>
<CharacterType>2</CharacterType>
<InternalID>8</InternalID>
<PopSpeed>120</PopSpeed>
<isPTBoss>0</isPTBoss>
<PopPoint_X>245.34</PopPoint_X>
<PopPoint_Y>121.25</PopPoint_Y>
</Character>
<Character id="cUid21">
<CharacterUID>21</CharacterUID>
<CharacterName>オーガ</CharacterName>
<CharacterType>2</CharacterType>
<InternalID>8</InternalID>
<PopSpeed>120</PopSpeed>
<isPTBoss>0</isPTBoss>
<PopPoint_X>240.68</PopPoint_X>
<PopPoint_Y>128.75</PopPoint_Y>
</Character>
<Character id="cUid24">
<CharacterUID>24</CharacterUID>
<CharacterName>オーガ</CharacterName>
<CharacterType>2</CharacterType>
<InternalID>8</InternalID>
<PopSpeed>120</PopSpeed>
<isPTBoss>0</isPTBoss>
<PopPoint_X>66.70</PopPoint_X>
<PopPoint_Y>114.89</PopPoint_Y>
</Character>
<Character id="cUid26">
<CharacterUID>26</CharacterUID>
<CharacterName>オーガ</CharacterName>
<CharacterType>2</CharacterType>
<InternalID>8</InternalID>
<PopSpeed>120</PopSpeed>
<isPTBoss>0</isPTBoss>
<PopPoint_X>76.82</PopPoint_X>
<PopPoint_Y>127.50</PopPoint_Y>
</Character>
<Character id="cUid27">
<CharacterUID>27</CharacterUID>
<CharacterName>オーガソルジャー</CharacterName>
<CharacterType>2</CharacterType>
<InternalID>9</InternalID>
<PopSpeed>120</PopSpeed>
<isPTBoss>0</isPTBoss>
<PopPoint_X>69.20</PopPoint_X>
<PopPoint_Y>140.00</PopPoint_Y>
</Character>
<Character id="cUid29">
<CharacterUID>29</CharacterUID>
<CharacterName>オーガソルジャー</CharacterName>
<CharacterType>2</CharacterType>
<InternalID>9</InternalID>
<PopSpeed>120</PopSpeed>
<isPTBoss>0</isPTBoss>
<PopPoint_X>65.68</PopPoint_X>
<PopPoint_Y>70.57</PopPoint_Y>
</Character>
<Character id="cUid31">
<CharacterUID>31</CharacterUID>
<CharacterName>オーガソルジャー</CharacterName>
<CharacterType>2</CharacterType>
<InternalID>9</InternalID>
<PopSpeed>120</PopSpeed>
<isPTBoss>0</isPTBoss>
<PopPoint_X>71.82</PopPoint_X>
<PopPoint_Y>78.52</PopPoint_Y>
</Character>
<Character id="cUid32">
<CharacterUID>32</CharacterUID>
<CharacterName>オーガソルジャー</CharacterName>
<CharacterType>2</CharacterType>
<InternalID>9</InternalID>
<PopSpeed>120</PopSpeed>
<isPTBoss>0</isPTBoss>
<PopPoint_X>75.23</PopPoint_X>
<PopPoint_Y>72.84</PopPoint_Y>
</Character>
<Character id="cUid33">
<CharacterUID>33</CharacterUID>
<CharacterName>ゴーレム</CharacterName>
<CharacterType>2</CharacterType>
<InternalID>2</InternalID>
<PopSpeed>120</PopSpeed>
<isPTBoss>0</isPTBoss>
<PopPoint_X>180.91</PopPoint_X>
<PopPoint_Y>171.31</PopPoint_Y>
</Character>
<Character id="cUid35">
<CharacterUID>35</CharacterUID>
<CharacterName>ゴーレム</CharacterName>
<CharacterType>2</CharacterType>
<InternalID>2</InternalID>
<PopSpeed>120</PopSpeed>
<isPTBoss>0</isPTBoss>
<PopPoint_X>189.03</PopPoint_X>
<PopPoint_Y>178.58</PopPoint_Y>
</Character>
<Character id="cUid36">
<CharacterUID>36</CharacterUID>
<CharacterName>ゴーレム</CharacterName>
<CharacterType>2</CharacterType>
<InternalID>2</InternalID>
<PopSpeed>120</PopSpeed>
<isPTBoss>0</isPTBoss>
<PopPoint_X>180.34</PopPoint_X>
<PopPoint_Y>180.00</PopPoint_Y>
</Character>
<Character id="cUid37">
<CharacterUID>37</CharacterUID>
<CharacterName>ゴーレム</CharacterName>
<CharacterType>2</CharacterType>
<InternalID>2</InternalID>
<PopSpeed>120</PopSpeed>
<isPTBoss>0</isPTBoss>
<PopPoint_X>267.73</PopPoint_X>
<PopPoint_Y>160.34</PopPoint_Y>
</Character>
<Character id="cUid38">
<CharacterUID>38</CharacterUID>
<CharacterName>ゴーレム</CharacterName>
<CharacterType>2</CharacterType>
<InternalID>2</InternalID>
<PopSpeed>120</PopSpeed>
<isPTBoss>0</isPTBoss>
<PopPoint_X>259.38</PopPoint_X>
<PopPoint_Y>165.11</PopPoint_Y>
</Character>
<Character id="cUid40">
<CharacterUID>40</CharacterUID>
<CharacterName>ゴーレム</CharacterName>
<CharacterType>2</CharacterType>
<InternalID>2</InternalID>
<PopSpeed>120</PopSpeed>
<isPTBoss>0</isPTBoss>
<PopPoint_X>59.32</PopPoint_X>
<PopPoint_Y>118.30</PopPoint_Y>
</Character>
<Character id="cUid42">
<CharacterUID>42</CharacterUID>
<CharacterName>斧槍兵</CharacterName>
<CharacterType>2</CharacterType>
<InternalID>10</InternalID>
<PopSpeed>120</PopSpeed>
<isPTBoss>0</isPTBoss>
<PopPoint_X>26.02</PopPoint_X>
<PopPoint_Y>61.31</PopPoint_Y>
</Character>
<Character id="cUid43">
<CharacterUID>43</CharacterUID>
<CharacterName>斧槍兵</CharacterName>
<CharacterType>2</CharacterType>
<InternalID>10</InternalID>
<PopSpeed>120</PopSpeed>
<isPTBoss>0</isPTBoss>
<PopPoint_X>38.24</PopPoint_X>
<PopPoint_Y>49.43</PopPoint_Y>
</Character>
<Character id="cUid44">
<CharacterUID>44</CharacterUID>
<CharacterName>コートナイト</CharacterName>
<CharacterType>2</CharacterType>
<InternalID>11</InternalID>
<PopSpeed>120</PopSpeed>
<isPTBoss>0</isPTBoss>
<PopPoint_X>26.76</PopPoint_X>
<PopPoint_Y>49.26</PopPoint_Y>
</Character>
<Character id="cUid45">
<CharacterUID>45</CharacterUID>
<CharacterName>クレイゴーレム</CharacterName>
<CharacterType>2</CharacterType>
<InternalID>3</InternalID>
<PopSpeed>120</PopSpeed>
<isPTBoss>0</isPTBoss>
<PopPoint_X>16.59</PopPoint_X>
<PopPoint_Y>24.66</PopPoint_Y>
</Character>
<Character id="cUid46">
<CharacterUID>46</CharacterUID>
<CharacterName>マゴット</CharacterName>
<CharacterType>2</CharacterType>
<InternalID>1</InternalID>
<PopSpeed>120</PopSpeed>
<isPTBoss>0</isPTBoss>
<PopPoint_X>56.76</PopPoint_X>
<PopPoint_Y>21.70</PopPoint_Y>
</Character>
<Character id="cUid49">
<CharacterUID>49</CharacterUID>
<CharacterName>マゴット</CharacterName>
<CharacterType>2</CharacterType>
<InternalID>1</InternalID>
<PopSpeed>120</PopSpeed>
<isPTBoss>0</isPTBoss>
<PopPoint_X>68.86</PopPoint_X>
<PopPoint_Y>21.59</PopPoint_Y>
</Character>
<Character id="cUid50">
<CharacterUID>50</CharacterUID>
<CharacterName>マゴット</CharacterName>
<CharacterType>2</CharacterType>
<InternalID>1</InternalID>
<PopSpeed>120</PopSpeed>
<isPTBoss>0</isPTBoss>
<PopPoint_X>52.10</PopPoint_X>
<PopPoint_Y>14.26</PopPoint_Y>
</Character>
<Character id="cUid52">
<CharacterUID>52</CharacterUID>
<CharacterName>マーブルガゴイル</CharacterName>
<CharacterType>2</CharacterType>
<InternalID>0</InternalID>
<PopSpeed>120</PopSpeed>
<isPTBoss>0</isPTBoss>
<PopPoint_X>135.11</PopPoint_X>
<PopPoint_Y>22.95</PopPoint_Y>
</Character>
<Character id="cUid53">
<CharacterUID>53</CharacterUID>
<CharacterName>マーブルガゴイル</CharacterName>
<CharacterType>2</CharacterType>
<InternalID>0</InternalID>
<PopSpeed>120</PopSpeed>
<isPTBoss>0</isPTBoss>
<PopPoint_X>148.98</PopPoint_X>
<PopPoint_Y>22.95</PopPoint_Y>
</Character>
<Character id="cUid54">
<CharacterUID>54</CharacterUID>
<CharacterName>マーブルガゴイル</CharacterName>
<CharacterType>2</CharacterType>
<InternalID>0</InternalID>
<PopSpeed>120</PopSpeed>
<isPTBoss>0</isPTBoss>
<PopPoint_X>153.92</PopPoint_X>
<PopPoint_Y>20.85</PopPoint_Y>
</Character>
<Character id="cUid56">
<CharacterUID>56</CharacterUID>
<CharacterName>鷲闘士</CharacterName>
<CharacterType>2</CharacterType>
<InternalID>6</InternalID>
<PopSpeed>120</PopSpeed>
<isPTBoss>0</isPTBoss>
<PopPoint_X>198.35</PopPoint_X>
<PopPoint_Y>16.76</PopPoint_Y>
</Character>
<Character id="cUid57">
<CharacterUID>57</CharacterUID>
<CharacterName>鷲闘士</CharacterName>
<CharacterType>2</CharacterType>
<InternalID>6</InternalID>
<PopSpeed>120</PopSpeed>
<isPTBoss>0</isPTBoss>
<PopPoint_X>215.57</PopPoint_X>
<PopPoint_Y>17.27</PopPoint_Y>
</Character>
<Character id="cUid58">
<CharacterUID>58</CharacterUID>
<CharacterName>鷲闘士</CharacterName>
<CharacterType>2</CharacterType>
<InternalID>6</InternalID>
<PopSpeed>120</PopSpeed>
<isPTBoss>0</isPTBoss>
<PopPoint_X>228.41</PopPoint_X>
<PopPoint_Y>18.86</PopPoint_Y>
</Character>
<Character id="cUid59">
<CharacterUID>59</CharacterUID>
<CharacterName>コートナイト</CharacterName>
<CharacterType>2</CharacterType>
<InternalID>11</InternalID>
<PopSpeed>120</PopSpeed>
<isPTBoss>0</isPTBoss>
<PopPoint_X>254.09</PopPoint_X>
<PopPoint_Y>19.83</PopPoint_Y>
</Character>
<Character id="cUid60">
<CharacterUID>60</CharacterUID>
<CharacterName>コートナイト</CharacterName>
<CharacterType>2</CharacterType>
<InternalID>11</InternalID>
<PopSpeed>120</PopSpeed>
<isPTBoss>0</isPTBoss>
<PopPoint_X>265.28</PopPoint_X>
<PopPoint_Y>21.76</PopPoint_Y>
</Character>
<Character id="cUid61">
<CharacterUID>61</CharacterUID>
<CharacterName>レッドアイ護衛兵</CharacterName>
<CharacterType>2</CharacterType>
<InternalID>12</InternalID>
<PopSpeed>120</PopSpeed>
<isPTBoss>0</isPTBoss>
<PopPoint_X>371.36</PopPoint_X>
<PopPoint_Y>26.88</PopPoint_Y>
</Character>
<Character id="cUid62">
<CharacterUID>62</CharacterUID>
<CharacterName>レッドアイ護衛兵</CharacterName>
<CharacterType>2</CharacterType>
<InternalID>12</InternalID>
<PopSpeed>120</PopSpeed>
<isPTBoss>0</isPTBoss>
<PopPoint_X>366.82</PopPoint_X>
<PopPoint_Y>32.61</PopPoint_Y>
</Character>
<Character id="cUid63">
<CharacterUID>63</CharacterUID>
<CharacterName>レッドアイ護衛兵</CharacterName>
<CharacterType>2</CharacterType>
<InternalID>12</InternalID>
<PopSpeed>120</PopSpeed>
<isPTBoss>0</isPTBoss>
<PopPoint_X>375.34</PopPoint_X>
<PopPoint_Y>41.25</PopPoint_Y>
</Character>
<Character id="cUid64">
<CharacterUID>64</CharacterUID>
<CharacterName>鷲戦士</CharacterName>
<CharacterType>2</CharacterType>
<InternalID>5</InternalID>
<PopSpeed>120</PopSpeed>
<isPTBoss>0</isPTBoss>
<PopPoint_X>301.25</PopPoint_X>
<PopPoint_Y>44.66</PopPoint_Y>
</Character>
<Character id="cUid65">
<CharacterUID>65</CharacterUID>
<CharacterName>鷲戦士</CharacterName>
<CharacterType>2</CharacterType>
<InternalID>5</InternalID>
<PopSpeed>120</PopSpeed>
<isPTBoss>0</isPTBoss>
<PopPoint_X>306.99</PopPoint_X>
<PopPoint_Y>55.40</PopPoint_Y>
</Character>
<Character id="cUid66">
<CharacterUID>66</CharacterUID>
<CharacterName>斧槍兵</CharacterName>
<CharacterType>2</CharacterType>
<InternalID>10</InternalID>
<PopSpeed>120</PopSpeed>
<isPTBoss>0</isPTBoss>
<PopPoint_X>311.53</PopPoint_X>
<PopPoint_Y>72.05</PopPoint_Y>
</Character>
<Character id="cUid67">
<CharacterUID>67</CharacterUID>
<CharacterName>斧槍兵</CharacterName>
<CharacterType>2</CharacterType>
<InternalID>10</InternalID>
<PopSpeed>120</PopSpeed>
<isPTBoss>0</isPTBoss>
<PopPoint_X>323.98</PopPoint_X>
<PopPoint_Y>70.00</PopPoint_Y>
</Character>
<Character id="cUid68">
<CharacterUID>68</CharacterUID>
<CharacterName>ロックゴーレム</CharacterName>
<CharacterType>2</CharacterType>
<InternalID>4</InternalID>
<PopSpeed>120</PopSpeed>
<isPTBoss>0</isPTBoss>
<PopPoint_X>19.43</PopPoint_X>
<PopPoint_Y>169.77</PopPoint_Y>
</Character>
<Character id="cUid69">
<CharacterUID>69</CharacterUID>
<CharacterName>ロックゴーレム</CharacterName>
<CharacterType>2</CharacterType>
<InternalID>4</InternalID>
<PopSpeed>120</PopSpeed>
<isPTBoss>0</isPTBoss>
<PopPoint_X>16.76</PopPoint_X>
<PopPoint_Y>181.08</PopPoint_Y>
</Character>
<Character id="cUid70">
<CharacterUID>70</CharacterUID>
<CharacterName>コートナイト</CharacterName>
<CharacterType>2</CharacterType>
<InternalID>11</InternalID>
<PopSpeed>120</PopSpeed>
<isPTBoss>0</isPTBoss>
<PopPoint_X>50.85</PopPoint_X>
<PopPoint_Y>178.18</PopPoint_Y>
</Character>
<Character id="cUid72">
<CharacterUID>72</CharacterUID>
<CharacterName>レッドアイ護衛兵</CharacterName>
<CharacterType>2</CharacterType>
<InternalID>12</InternalID>
<PopSpeed>120</PopSpeed>
<isPTBoss>0</isPTBoss>
<PopPoint_X>52.90</PopPoint_X>
<PopPoint_Y>186.42</PopPoint_Y>
</Character>
<Character id="cUid73">
<CharacterUID>73</CharacterUID>
<CharacterName>レッドアイ護衛兵</CharacterName>
<CharacterType>2</CharacterType>
<InternalID>12</InternalID>
<PopSpeed>120</PopSpeed>
<isPTBoss>0</isPTBoss>
<PopPoint_X>140.68</PopPoint_X>
<PopPoint_Y>183.01</PopPoint_Y>
</Character>
<Character id="cUid74">
<CharacterUID>74</CharacterUID>
<CharacterName>レッドアイ護衛兵</CharacterName>
<CharacterType>2</CharacterType>
<InternalID>12</InternalID>
<PopSpeed>120</PopSpeed>
<isPTBoss>0</isPTBoss>
<PopPoint_X>132.90</PopPoint_X>
<PopPoint_Y>188.98</PopPoint_Y>
</Character>
<Character id="cUid75">
<CharacterUID>75</CharacterUID>
<CharacterName>ロックゴーレム</CharacterName>
<CharacterType>2</CharacterType>
<InternalID>4</InternalID>
<PopSpeed>120</PopSpeed>
<isPTBoss>0</isPTBoss>
<PopPoint_X>309.32</PopPoint_X>
<PopPoint_Y>99.66</PopPoint_Y>
</Character>
<Character id="cUid76">
<CharacterUID>76</CharacterUID>
<CharacterName>クレイゴーレム</CharacterName>
<CharacterType>2</CharacterType>
<InternalID>3</InternalID>
<PopSpeed>120</PopSpeed>
<isPTBoss>0</isPTBoss>
<PopPoint_X>305.97</PopPoint_X>
<PopPoint_Y>106.02</PopPoint_Y>
</Character>
<Character id="cUid77">
<CharacterUID>77</CharacterUID>
<CharacterName>鷲戦士</CharacterName>
<CharacterType>2</CharacterType>
<InternalID>5</InternalID>
<PopSpeed>120</PopSpeed>
<isPTBoss>0</isPTBoss>
<PopPoint_X>303.69</PopPoint_X>
<PopPoint_Y>143.52</PopPoint_Y>
</Character>
<Character id="cUid78">
<CharacterUID>78</CharacterUID>
<CharacterName>ロックゴーレム</CharacterName>
<CharacterType>2</CharacterType>
<InternalID>4</InternalID>
<PopSpeed>120</PopSpeed>
<isPTBoss>0</isPTBoss>
<PopPoint_X>302.44</PopPoint_X>
<PopPoint_Y>154.66</PopPoint_Y>
</Character>
<Character id="cUid79">
<CharacterUID>79</CharacterUID>
<CharacterName>ロックゴーレム</CharacterName>
<CharacterType>2</CharacterType>
<InternalID>4</InternalID>
<PopSpeed>120</PopSpeed>
<isPTBoss>0</isPTBoss>
<PopPoint_X>297.27</PopPoint_X>
<PopPoint_Y>164.09</PopPoint_Y>
</Character>
<Character id="cUid80">
<CharacterUID>80</CharacterUID>
<CharacterName>鷲闘士</CharacterName>
<CharacterType>2</CharacterType>
<InternalID>6</InternalID>
<PopSpeed>120</PopSpeed>
<isPTBoss>0</isPTBoss>
<PopPoint_X>313.75</PopPoint_X>
<PopPoint_Y>185.68</PopPoint_Y>
</Character>
<Character id="cUid81">
<CharacterUID>81</CharacterUID>
<CharacterName>鷲闘士</CharacterName>
<CharacterType>2</CharacterType>
<InternalID>6</InternalID>
<PopSpeed>120</PopSpeed>
<isPTBoss>0</isPTBoss>
<PopPoint_X>324.38</PopPoint_X>
<PopPoint_Y>188.41</PopPoint_Y>
</Character>
<Character id="cUid83">
<CharacterUID>83</CharacterUID>
<CharacterName>鷲戦士</CharacterName>
<CharacterType>2</CharacterType>
<InternalID>5</InternalID>
<PopSpeed>120</PopSpeed>
<isPTBoss>0</isPTBoss>
<PopPoint_X>386.88</PopPoint_X>
<PopPoint_Y>175.51</PopPoint_Y>
</Character>
<Character id="cUid84">
<CharacterUID>84</CharacterUID>
<CharacterName>鷲戦士</CharacterName>
<CharacterType>2</CharacterType>
<InternalID>5</InternalID>
<PopSpeed>120</PopSpeed>
<isPTBoss>0</isPTBoss>
<PopPoint_X>378.81</PopPoint_X>
<PopPoint_Y>183.07</PopPoint_Y>
</Character>
</CharacterData>
<AreaData>
<Area id="aUid0">
<AreaUID>0</AreaUID>
<AreaName>_필드 전체</AreaName>
<AreaType>0</AreaType>
<AccessMap></AccessMap>
<AccessMapName></AccessMapName>
<AreaPos_X>0.00</AreaPos_X>
<AreaPos_X2>0.00</AreaPos_X2>
<AreaPos_Y>0.00</AreaPos_Y>
<AreaPos_Y2>0.00</AreaPos_Y2>
<AreaExpansion>
</AreaExpansion>
</Area>
<Area id="aUid1">
<AreaUID>1</AreaUID>
<AreaName>_화면</AreaName>
<AreaType>0</AreaType>
<AccessMap></AccessMap>
<AccessMapName></AccessMapName>
<AreaPos_X>0.00</AreaPos_X>
<AreaPos_X2>0.00</AreaPos_X2>
<AreaPos_Y>0.00</AreaPos_Y>
<AreaPos_Y2>0.00</AreaPos_Y2>
<AreaExpansion>
</AreaExpansion>
</Area>
<Area id="aUid2">
<AreaUID>2</AreaUID>
<AreaName>시작 영역</AreaName>
<AreaType>5</AreaType>
<AccessMap></AccessMap>
<AccessMapName></AccessMapName>
<AreaPos_X>175.40</AreaPos_X>
<AreaPos_X2>195.97</AreaPos_X2>
<AreaPos_Y>78.98</AreaPos_Y>
<AreaPos_Y2>92.95</AreaPos_Y2>
<AreaExpansion>
</AreaExpansion>
</Area>
<Area id="aUid3">
<AreaUID>3</AreaUID>
<AreaName>01</AreaName>
<AreaType>2</AreaType>
<AccessMap></AccessMap>
<AccessMapName></AccessMapName>
<AreaPos_X>98.13</AreaPos_X>
<AreaPos_X2>112.16</AreaPos_X2>
<AreaPos_Y>5.23</AreaPos_Y>
<AreaPos_Y2>19.66</AreaPos_Y2>
<AreaExpansion>
<Door_Endurance>10000</Door_Endurance>
<DetectSecretDoor_Lv>0</DetectSecretDoor_Lv>
<UnlockDoor_Lv>0</UnlockDoor_Lv>
<RecoveryTime>30</RecoveryTime>
<isMortalObject>1</isMortalObject>
<DisarmTrap_Lv>0</DisarmTrap_Lv>
<DetectTrap_Lv>0</DetectTrap_Lv>
<TrapID1>65535</TrapID1>
<TrapID2>65535</TrapID2>
<isSecretDungeonEntrance>0</isSecretDungeonEntrance>
</AreaExpansion>
</Area>
<Area id="aUid4">
<AreaUID>4</AreaUID>
<AreaName>02</AreaName>
<AreaType>2</AreaType>
<AccessMap></AccessMap>
<AccessMapName></AccessMapName>
<AreaPos_X>9.20</AreaPos_X>
<AreaPos_X2>26.36</AreaPos_X2>
<AreaPos_Y>72.50</AreaPos_Y>
<AreaPos_Y2>85.68</AreaPos_Y2>
<AreaExpansion>
<Door_Endurance>10000</Door_Endurance>
<DetectSecretDoor_Lv>0</DetectSecretDoor_Lv>
<UnlockDoor_Lv>0</UnlockDoor_Lv>
<RecoveryTime>30</RecoveryTime>
<isMortalObject>1</isMortalObject>
<DisarmTrap_Lv>0</DisarmTrap_Lv>
<DetectTrap_Lv>0</DetectTrap_Lv>
<TrapID1>65535</TrapID1>
<TrapID2>65535</TrapID2>
<isSecretDungeonEntrance>0</isSecretDungeonEntrance>
</AreaExpansion>
</Area>
<Area id="aUid5">
<AreaUID>5</AreaUID>
<AreaName>03</AreaName>
<AreaType>2</AreaType>
<AccessMap></AccessMap>
<AccessMapName></AccessMapName>
<AreaPos_X>25.57</AreaPos_X>
<AreaPos_X2>41.70</AreaPos_X2>
<AreaPos_Y>90.68</AreaPos_Y>
<AreaPos_Y2>104.20</AreaPos_Y2>
<AreaExpansion>
<Door_Endurance>10000</Door_Endurance>
<DetectSecretDoor_Lv>0</DetectSecretDoor_Lv>
<UnlockDoor_Lv>0</UnlockDoor_Lv>
<RecoveryTime>30</RecoveryTime>
<isMortalObject>1</isMortalObject>
<DisarmTrap_Lv>0</DisarmTrap_Lv>
<DetectTrap_Lv>0</DetectTrap_Lv>
<TrapID1>65535</TrapID1>
<TrapID2>65535</TrapID2>
<isSecretDungeonEntrance>0</isSecretDungeonEntrance>
</AreaExpansion>
</Area>
<Area id="aUid6">
<AreaUID>6</AreaUID>
<AreaName>04</AreaName>
<AreaType>2</AreaType>
<AccessMap></AccessMap>
<AccessMapName></AccessMapName>
<AreaPos_X>16.70</AreaPos_X>
<AreaPos_X2>31.02</AreaPos_X2>
<AreaPos_Y>112.16</AreaPos_Y>
<AreaPos_Y2>126.59</AreaPos_Y2>
<AreaExpansion>
<Door_Endurance>10000</Door_Endurance>
<DetectSecretDoor_Lv>0</DetectSecretDoor_Lv>
<UnlockDoor_Lv>0</UnlockDoor_Lv>
<RecoveryTime>30</RecoveryTime>
<isMortalObject>1</isMortalObject>
<DisarmTrap_Lv>0</DisarmTrap_Lv>
<DetectTrap_Lv>0</DetectTrap_Lv>
<TrapID1>65535</TrapID1>
<TrapID2>65535</TrapID2>
<isSecretDungeonEntrance>0</isSecretDungeonEntrance>
</AreaExpansion>
</Area>
<Area id="aUid7">
<AreaUID>7</AreaUID>
<AreaName>05</AreaName>
<AreaType>2</AreaType>
<AccessMap></AccessMap>
<AccessMapName></AccessMapName>
<AreaPos_X>18.98</AreaPos_X>
<AreaPos_X2>33.64</AreaPos_X2>
<AreaPos_Y>143.86</AreaPos_Y>
<AreaPos_Y2>157.84</AreaPos_Y2>
<AreaExpansion>
<Door_Endurance>10000</Door_Endurance>
<DetectSecretDoor_Lv>0</DetectSecretDoor_Lv>
<UnlockDoor_Lv>0</UnlockDoor_Lv>
<RecoveryTime>30</RecoveryTime>
<isMortalObject>1</isMortalObject>
<DisarmTrap_Lv>0</DisarmTrap_Lv>
<DetectTrap_Lv>0</DetectTrap_Lv>
<TrapID1>65535</TrapID1>
<TrapID2>65535</TrapID2>
<isSecretDungeonEntrance>0</isSecretDungeonEntrance>
</AreaExpansion>
</Area>
<Area id="aUid8">
<AreaUID>8</AreaUID>
<AreaName>06</AreaName>
<AreaType>2</AreaType>
<AccessMap></AccessMap>
<AccessMapName></AccessMapName>
<AreaPos_X>70.11</AreaPos_X>
<AreaPos_X2>84.20</AreaPos_X2>
<AreaPos_Y>157.16</AreaPos_Y>
<AreaPos_Y2>170.68</AreaPos_Y2>
<AreaExpansion>
<Door_Endurance>10000</Door_Endurance>
<DetectSecretDoor_Lv>0</DetectSecretDoor_Lv>
<UnlockDoor_Lv>0</UnlockDoor_Lv>
<RecoveryTime>30</RecoveryTime>
<isMortalObject>1</isMortalObject>
<DisarmTrap_Lv>0</DisarmTrap_Lv>
<DetectTrap_Lv>0</DetectTrap_Lv>
<TrapID1>65535</TrapID1>
<TrapID2>65535</TrapID2>
<isSecretDungeonEntrance>0</isSecretDungeonEntrance>
</AreaExpansion>
</Area>
<Area id="aUid9">
<AreaUID>9</AreaUID>
<AreaName>07</AreaName>
<AreaType>2</AreaType>
<AccessMap></AccessMap>
<AccessMapName></AccessMapName>
<AreaPos_X>106.14</AreaPos_X>
<AreaPos_X2>119.09</AreaPos_X2>
<AreaPos_Y>169.55</AreaPos_Y>
<AreaPos_Y2>182.50</AreaPos_Y2>
<AreaExpansion>
<Door_Endurance>10000</Door_Endurance>
<DetectSecretDoor_Lv>0</DetectSecretDoor_Lv>
<UnlockDoor_Lv>0</UnlockDoor_Lv>
<RecoveryTime>30</RecoveryTime>
<isMortalObject>1</isMortalObject>
<DisarmTrap_Lv>0</DisarmTrap_Lv>
<DetectTrap_Lv>0</DetectTrap_Lv>
<TrapID1>65535</TrapID1>
<TrapID2>65535</TrapID2>
<isSecretDungeonEntrance>0</isSecretDungeonEntrance>
</AreaExpansion>
</Area>
<Area id="aUid10">
<AreaUID>10</AreaUID>
<AreaName>08</AreaName>
<AreaType>2</AreaType>
<AccessMap></AccessMap>
<AccessMapName></AccessMapName>
<AreaPos_X>97.39</AreaPos_X>
<AreaPos_X2>111.25</AreaPos_X2>
<AreaPos_Y>139.66</AreaPos_Y>
<AreaPos_Y2>151.14</AreaPos_Y2>
<AreaExpansion>
<Door_Endurance>10000</Door_Endurance>
<DetectSecretDoor_Lv>0</DetectSecretDoor_Lv>
<UnlockDoor_Lv>0</UnlockDoor_Lv>
<RecoveryTime>30</RecoveryTime>
<isMortalObject>1</isMortalObject>
<DisarmTrap_Lv>0</DisarmTrap_Lv>
<DetectTrap_Lv>0</DetectTrap_Lv>
<TrapID1>65535</TrapID1>
<TrapID2>65535</TrapID2>
<isSecretDungeonEntrance>0</isSecretDungeonEntrance>
</AreaExpansion>
</Area>
<Area id="aUid11">
<AreaUID>11</AreaUID>
<AreaName>09</AreaName>
<AreaType>2</AreaType>
<AccessMap></AccessMap>
<AccessMapName></AccessMapName>
<AreaPos_X>95.23</AreaPos_X>
<AreaPos_X2>107.84</AreaPos_X2>
<AreaPos_Y>94.43</AreaPos_Y>
<AreaPos_Y2>107.73</AreaPos_Y2>
<AreaExpansion>
<Door_Endurance>10000</Door_Endurance>
<DetectSecretDoor_Lv>0</DetectSecretDoor_Lv>
<UnlockDoor_Lv>0</UnlockDoor_Lv>
<RecoveryTime>30</RecoveryTime>
<isMortalObject>1</isMortalObject>
<DisarmTrap_Lv>0</DisarmTrap_Lv>
<DetectTrap_Lv>0</DetectTrap_Lv>
<TrapID1>65535</TrapID1>
<TrapID2>65535</TrapID2>
<isSecretDungeonEntrance>0</isSecretDungeonEntrance>
</AreaExpansion>
</Area>
<Area id="aUid12">
<AreaUID>12</AreaUID>
<AreaName>10</AreaName>
<AreaType>2</AreaType>
<AccessMap></AccessMap>
<AccessMapName></AccessMapName>
<AreaPos_X>74.66</AreaPos_X>
<AreaPos_X2>88.30</AreaPos_X2>
<AreaPos_Y>53.07</AreaPos_Y>
<AreaPos_Y2>65.68</AreaPos_Y2>
<AreaExpansion>
<Door_Endurance>10000</Door_Endurance>
<DetectSecretDoor_Lv>0</DetectSecretDoor_Lv>
<UnlockDoor_Lv>0</UnlockDoor_Lv>
<RecoveryTime>30</RecoveryTime>
<isMortalObject>1</isMortalObject>
<DisarmTrap_Lv>0</DisarmTrap_Lv>
<DetectTrap_Lv>0</DetectTrap_Lv>
<TrapID1>65535</TrapID1>
<TrapID2>65535</TrapID2>
<isSecretDungeonEntrance>0</isSecretDungeonEntrance>
</AreaExpansion>
</Area>
<Area id="aUid13">
<AreaUID>13</AreaUID>
<AreaName>11</AreaName>
<AreaType>2</AreaType>
<AccessMap></AccessMap>
<AccessMapName></AccessMapName>
<AreaPos_X>111.70</AreaPos_X>
<AreaPos_X2>127.50</AreaPos_X2>
<AreaPos_Y>31.82</AreaPos_Y>
<AreaPos_Y2>44.55</AreaPos_Y2>
<AreaExpansion>
<Door_Endurance>10000</Door_Endurance>
<DetectSecretDoor_Lv>0</DetectSecretDoor_Lv>
<UnlockDoor_Lv>0</UnlockDoor_Lv>
<RecoveryTime>30</RecoveryTime>
<isMortalObject>1</isMortalObject>
<DisarmTrap_Lv>0</DisarmTrap_Lv>
<DetectTrap_Lv>0</DetectTrap_Lv>
<TrapID1>65535</TrapID1>
<TrapID2>65535</TrapID2>
<isSecretDungeonEntrance>0</isSecretDungeonEntrance>
</AreaExpansion>
</Area>
<Area id="aUid14">
<AreaUID>14</AreaUID>
<AreaName>12</AreaName>
<AreaType>2</AreaType>
<AccessMap></AccessMap>
<AccessMapName></AccessMapName>
<AreaPos_X>137.73</AreaPos_X>
<AreaPos_X2>150.45</AreaPos_X2>
<AreaPos_Y>40.68</AreaPos_Y>
<AreaPos_Y2>52.73</AreaPos_Y2>
<AreaExpansion>
<Door_Endurance>10000</Door_Endurance>
<DetectSecretDoor_Lv>0</DetectSecretDoor_Lv>
<UnlockDoor_Lv>0</UnlockDoor_Lv>
<RecoveryTime>30</RecoveryTime>
<isMortalObject>1</isMortalObject>
<DisarmTrap_Lv>0</DisarmTrap_Lv>
<DetectTrap_Lv>0</DetectTrap_Lv>
<TrapID1>65535</TrapID1>
<TrapID2>65535</TrapID2>
<isSecretDungeonEntrance>0</isSecretDungeonEntrance>
</AreaExpansion>
</Area>
<Area id="aUid15">
<AreaUID>15</AreaUID>
<AreaName>13</AreaName>
<AreaType>2</AreaType>
<AccessMap></AccessMap>
<AccessMapName></AccessMapName>
<AreaPos_X>160.11</AreaPos_X>
<AreaPos_X2>173.52</AreaPos_X2>
<AreaPos_Y>99.32</AreaPos_Y>
<AreaPos_Y2>112.73</AreaPos_Y2>
<AreaExpansion>
<Door_Endurance>10000</Door_Endurance>
<DetectSecretDoor_Lv>0</DetectSecretDoor_Lv>
<UnlockDoor_Lv>0</UnlockDoor_Lv>
<RecoveryTime>30</RecoveryTime>
<isMortalObject>1</isMortalObject>
<DisarmTrap_Lv>0</DisarmTrap_Lv>
<DetectTrap_Lv>0</DetectTrap_Lv>
<TrapID1>65535</TrapID1>
<TrapID2>65535</TrapID2>
<isSecretDungeonEntrance>0</isSecretDungeonEntrance>
</AreaExpansion>
</Area>
<Area id="aUid16">
<AreaUID>16</AreaUID>
<AreaName>14</AreaName>
<AreaType>2</AreaType>
<AccessMap></AccessMap>
<AccessMapName></AccessMapName>
<AreaPos_X>210.45</AreaPos_X>
<AreaPos_X2>222.50</AreaPos_X2>
<AreaPos_Y>100.57</AreaPos_Y>
<AreaPos_Y2>112.84</AreaPos_Y2>
<AreaExpansion>
<Door_Endurance>10000</Door_Endurance>
<DetectSecretDoor_Lv>0</DetectSecretDoor_Lv>
<UnlockDoor_Lv>0</UnlockDoor_Lv>
<RecoveryTime>30</RecoveryTime>
<isMortalObject>1</isMortalObject>
<DisarmTrap_Lv>0</DisarmTrap_Lv>
<DetectTrap_Lv>0</DetectTrap_Lv>
<TrapID1>65535</TrapID1>
<TrapID2>65535</TrapID2>
<isSecretDungeonEntrance>0</isSecretDungeonEntrance>
</AreaExpansion>
</Area>
<Area id="aUid17">
<AreaUID>17</AreaUID>
<AreaName>15</AreaName>
<AreaType>2</AreaType>
<AccessMap></AccessMap>
<AccessMapName></AccessMapName>
<AreaPos_X>138.52</AreaPos_X>
<AreaPos_X2>151.48</AreaPos_X2>
<AreaPos_Y>146.70</AreaPos_Y>
<AreaPos_Y2>161.48</AreaPos_Y2>
<AreaExpansion>
<Door_Endurance>10000</Door_Endurance>
<DetectSecretDoor_Lv>0</DetectSecretDoor_Lv>
<UnlockDoor_Lv>0</UnlockDoor_Lv>
<RecoveryTime>30</RecoveryTime>
<isMortalObject>1</isMortalObject>
<DisarmTrap_Lv>0</DisarmTrap_Lv>
<DetectTrap_Lv>0</DetectTrap_Lv>
<TrapID1>65535</TrapID1>
<TrapID2>65535</TrapID2>
<isSecretDungeonEntrance>0</isSecretDungeonEntrance>
</AreaExpansion>
</Area>
<Area id="aUid18">
<AreaUID>18</AreaUID>
<AreaName>16</AreaName>
<AreaType>2</AreaType>
<AccessMap></AccessMap>
<AccessMapName></AccessMapName>
<AreaPos_X>176.82</AreaPos_X>
<AreaPos_X2>189.89</AreaPos_X2>
<AreaPos_Y>129.20</AreaPos_Y>
<AreaPos_Y2>140.57</AreaPos_Y2>
<AreaExpansion>
<Door_Endurance>10000</Door_Endurance>
<DetectSecretDoor_Lv>0</DetectSecretDoor_Lv>
<UnlockDoor_Lv>0</UnlockDoor_Lv>
<RecoveryTime>30</RecoveryTime>
<isMortalObject>1</isMortalObject>
<DisarmTrap_Lv>0</DisarmTrap_Lv>
<DetectTrap_Lv>0</DetectTrap_Lv>
<TrapID1>65535</TrapID1>
<TrapID2>65535</TrapID2>
<isSecretDungeonEntrance>0</isSecretDungeonEntrance>
</AreaExpansion>
</Area>
<Area id="aUid19">
<AreaUID>19</AreaUID>
<AreaName>17</AreaName>
<AreaType>2</AreaType>
<AccessMap></AccessMap>
<AccessMapName></AccessMapName>
<AreaPos_X>207.39</AreaPos_X>
<AreaPos_X2>219.89</AreaPos_X2>
<AreaPos_Y>172.61</AreaPos_Y>
<AreaPos_Y2>186.36</AreaPos_Y2>
<AreaExpansion>
<Door_Endurance>10000</Door_Endurance>
<DetectSecretDoor_Lv>0</DetectSecretDoor_Lv>
<UnlockDoor_Lv>0</UnlockDoor_Lv>
<RecoveryTime>30</RecoveryTime>
<isMortalObject>1</isMortalObject>
<DisarmTrap_Lv>0</DisarmTrap_Lv>
<DetectTrap_Lv>0</DetectTrap_Lv>
<TrapID1>65535</TrapID1>
<TrapID2>65535</TrapID2>
<isSecretDungeonEntrance>0</isSecretDungeonEntrance>
</AreaExpansion>
</Area>
<Area id="aUid20">
<AreaUID>20</AreaUID>
<AreaName>18</AreaName>
<AreaType>2</AreaType>
<AccessMap></AccessMap>
<AccessMapName></AccessMapName>
<AreaPos_X>274.77</AreaPos_X>
<AreaPos_X2>288.41</AreaPos_X2>
<AreaPos_Y>173.86</AreaPos_Y>
<AreaPos_Y2>186.70</AreaPos_Y2>
<AreaExpansion>
<Door_Endurance>10000</Door_Endurance>
<DetectSecretDoor_Lv>0</DetectSecretDoor_Lv>
<UnlockDoor_Lv>0</UnlockDoor_Lv>
<RecoveryTime>30</RecoveryTime>
<isMortalObject>1</isMortalObject>
<DisarmTrap_Lv>0</DisarmTrap_Lv>
<DetectTrap_Lv>0</DetectTrap_Lv>
<TrapID1>65535</TrapID1>
<TrapID2>65535</TrapID2>
<isSecretDungeonEntrance>0</isSecretDungeonEntrance>
</AreaExpansion>
</Area>
<Area id="aUid21">
<AreaUID>21</AreaUID>
<AreaName>19</AreaName>
<AreaType>2</AreaType>
<AccessMap></AccessMap>
<AccessMapName></AccessMapName>
<AreaPos_X>275.91</AreaPos_X>
<AreaPos_X2>288.64</AreaPos_X2>
<AreaPos_Y>112.05</AreaPos_Y>
<AreaPos_Y2>123.64</AreaPos_Y2>
<AreaExpansion>
<Door_Endurance>10000</Door_Endurance>
<DetectSecretDoor_Lv>0</DetectSecretDoor_Lv>
<UnlockDoor_Lv>0</UnlockDoor_Lv>
<RecoveryTime>30</RecoveryTime>
<isMortalObject>1</isMortalObject>
<DisarmTrap_Lv>0</DisarmTrap_Lv>
<DetectTrap_Lv>0</DetectTrap_Lv>
<TrapID1>65535</TrapID1>
<TrapID2>65535</TrapID2>
<isSecretDungeonEntrance>0</isSecretDungeonEntrance>
</AreaExpansion>
</Area>
<Area id="aUid22">
<AreaUID>22</AreaUID>
<AreaName>20</AreaName>
<AreaType>2</AreaType>
<AccessMap></AccessMap>
<AccessMapName></AccessMapName>
<AreaPos_X>217.95</AreaPos_X>
<AreaPos_X2>233.41</AreaPos_X2>
<AreaPos_Y>57.50</AreaPos_Y>
<AreaPos_Y2>70.45</AreaPos_Y2>
<AreaExpansion>
<Door_Endurance>10000</Door_Endurance>
<DetectSecretDoor_Lv>0</DetectSecretDoor_Lv>
<UnlockDoor_Lv>0</UnlockDoor_Lv>
<RecoveryTime>30</RecoveryTime>
<isMortalObject>1</isMortalObject>
<DisarmTrap_Lv>0</DisarmTrap_Lv>
<DetectTrap_Lv>0</DetectTrap_Lv>
<TrapID1>65535</TrapID1>
<TrapID2>65535</TrapID2>
<isSecretDungeonEntrance>0</isSecretDungeonEntrance>
</AreaExpansion>
</Area>
<Area id="aUid23">
<AreaUID>23</AreaUID>
<AreaName>21</AreaName>
<AreaType>2</AreaType>
<AccessMap></AccessMap>
<AccessMapName></AccessMapName>
<AreaPos_X>248.75</AreaPos_X>
<AreaPos_X2>263.86</AreaPos_X2>
<AreaPos_Y>3.07</AreaPos_Y>
<AreaPos_Y2>16.93</AreaPos_Y2>
<AreaExpansion>
<Door_Endurance>10000</Door_Endurance>
<DetectSecretDoor_Lv>0</DetectSecretDoor_Lv>
<UnlockDoor_Lv>0</UnlockDoor_Lv>
<RecoveryTime>30</RecoveryTime>
<isMortalObject>1</isMortalObject>
<DisarmTrap_Lv>0</DisarmTrap_Lv>
<DetectTrap_Lv>0</DetectTrap_Lv>
<TrapID1>65535</TrapID1>
<TrapID2>65535</TrapID2>
<isSecretDungeonEntrance>0</isSecretDungeonEntrance>
</AreaExpansion>
</Area>
<Area id="aUid24">
<AreaUID>24</AreaUID>
<AreaName>22</AreaName>
<AreaType>2</AreaType>
<AccessMap></AccessMap>
<AccessMapName></AccessMapName>
<AreaPos_X>272.73</AreaPos_X>
<AreaPos_X2>290.45</AreaPos_X2>
<AreaPos_Y>37.50</AreaPos_Y>
<AreaPos_Y2>49.89</AreaPos_Y2>
<AreaExpansion>
<Door_Endurance>10000</Door_Endurance>
<DetectSecretDoor_Lv>0</DetectSecretDoor_Lv>
<UnlockDoor_Lv>0</UnlockDoor_Lv>
<RecoveryTime>30</RecoveryTime>
<isMortalObject>1</isMortalObject>
<DisarmTrap_Lv>0</DisarmTrap_Lv>
<DetectTrap_Lv>0</DetectTrap_Lv>
<TrapID1>65535</TrapID1>
<TrapID2>65535</TrapID2>
<isSecretDungeonEntrance>0</isSecretDungeonEntrance>
</AreaExpansion>
</Area>
<Area id="aUid25">
<AreaUID>25</AreaUID>
<AreaName>23</AreaName>
<AreaType>2</AreaType>
<AccessMap></AccessMap>
<AccessMapName></AccessMapName>
<AreaPos_X>274.43</AreaPos_X>
<AreaPos_X2>286.14</AreaPos_X2>
<AreaPos_Y>82.73</AreaPos_Y>
<AreaPos_Y2>95.45</AreaPos_Y2>
<AreaExpansion>
<Door_Endurance>10000</Door_Endurance>
<DetectSecretDoor_Lv>0</DetectSecretDoor_Lv>
<UnlockDoor_Lv>0</UnlockDoor_Lv>
<RecoveryTime>30</RecoveryTime>
<isMortalObject>1</isMortalObject>
<DisarmTrap_Lv>0</DisarmTrap_Lv>
<DetectTrap_Lv>0</DetectTrap_Lv>
<TrapID1>65535</TrapID1>
<TrapID2>65535</TrapID2>
<isSecretDungeonEntrance>0</isSecretDungeonEntrance>
</AreaExpansion>
</Area>
<Area id="aUid26">
<AreaUID>26</AreaUID>
<AreaName>24</AreaName>
<AreaType>2</AreaType>
<AccessMap></AccessMap>
<AccessMapName></AccessMapName>
<AreaPos_X>337.50</AreaPos_X>
<AreaPos_X2>352.50</AreaPos_X2>
<AreaPos_Y>177.73</AreaPos_Y>
<AreaPos_Y2>187.95</AreaPos_Y2>
<AreaExpansion>
<Door_Endurance>10000</Door_Endurance>
<DetectSecretDoor_Lv>0</DetectSecretDoor_Lv>
<UnlockDoor_Lv>0</UnlockDoor_Lv>
<RecoveryTime>30</RecoveryTime>
<isMortalObject>1</isMortalObject>
<DisarmTrap_Lv>0</DisarmTrap_Lv>
<DetectTrap_Lv>0</DetectTrap_Lv>
<TrapID1>65535</TrapID1>
<TrapID2>65535</TrapID2>
<isSecretDungeonEntrance>0</isSecretDungeonEntrance>
</AreaExpansion>
</Area>
<Area id="aUid27">
<AreaUID>27</AreaUID>
<AreaName>25</AreaName>
<AreaType>2</AreaType>
<AccessMap></AccessMap>
<AccessMapName></AccessMapName>
<AreaPos_X>353.75</AreaPos_X>
<AreaPos_X2>366.70</AreaPos_X2>
<AreaPos_Y>152.39</AreaPos_Y>
<AreaPos_Y2>163.07</AreaPos_Y2>
<AreaExpansion>
<Door_Endurance>10000</Door_Endurance>
<DetectSecretDoor_Lv>0</DetectSecretDoor_Lv>
<UnlockDoor_Lv>0</UnlockDoor_Lv>
<RecoveryTime>30</RecoveryTime>
<isMortalObject>1</isMortalObject>
<DisarmTrap_Lv>0</DisarmTrap_Lv>
<DetectTrap_Lv>0</DetectTrap_Lv>
<TrapID1>65535</TrapID1>
<TrapID2>65535</TrapID2>
<isSecretDungeonEntrance>0</isSecretDungeonEntrance>
</AreaExpansion>
</Area>
<Area id="aUid28">
<AreaUID>28</AreaUID>
<AreaName>26</AreaName>
<AreaType>2</AreaType>
<AccessMap></AccessMap>
<AccessMapName></AccessMapName>
<AreaPos_X>333.75</AreaPos_X>
<AreaPos_X2>347.61</AreaPos_X2>
<AreaPos_Y>127.16</AreaPos_Y>
<AreaPos_Y2>137.16</AreaPos_Y2>
<AreaExpansion>
<Door_Endurance>10000</Door_Endurance>
<DetectSecretDoor_Lv>0</DetectSecretDoor_Lv>
<UnlockDoor_Lv>0</UnlockDoor_Lv>
<RecoveryTime>30</RecoveryTime>
<isMortalObject>1</isMortalObject>
<DisarmTrap_Lv>0</DisarmTrap_Lv>
<DetectTrap_Lv>0</DetectTrap_Lv>
<TrapID1>65535</TrapID1>
<TrapID2>65535</TrapID2>
<isSecretDungeonEntrance>0</isSecretDungeonEntrance>
</AreaExpansion>
</Area>
<Area id="aUid29">
<AreaUID>29</AreaUID>
<AreaName>27</AreaName>
<AreaType>2</AreaType>
<AccessMap></AccessMap>
<AccessMapName></AccessMapName>
<AreaPos_X>334.20</AreaPos_X>
<AreaPos_X2>347.16</AreaPos_X2>
<AreaPos_Y>93.98</AreaPos_Y>
<AreaPos_Y2>104.09</AreaPos_Y2>
<AreaExpansion>
<Door_Endurance>10000</Door_Endurance>
<DetectSecretDoor_Lv>0</DetectSecretDoor_Lv>
<UnlockDoor_Lv>0</UnlockDoor_Lv>
<RecoveryTime>30</RecoveryTime>
<isMortalObject>1</isMortalObject>
<DisarmTrap_Lv>0</DisarmTrap_Lv>
<DetectTrap_Lv>0</DetectTrap_Lv>
<TrapID1>65535</TrapID1>
<TrapID2>65535</TrapID2>
<isSecretDungeonEntrance>0</isSecretDungeonEntrance>
</AreaExpansion>
</Area>
<Area id="aUid30">
<AreaUID>30</AreaUID>
<AreaName>28</AreaName>
<AreaType>2</AreaType>
<AccessMap></AccessMap>
<AccessMapName></AccessMapName>
<AreaPos_X>350.80</AreaPos_X>
<AreaPos_X2>365.57</AreaPos_X2>
<AreaPos_Y>81.59</AreaPos_Y>
<AreaPos_Y2>92.61</AreaPos_Y2>
<AreaExpansion>
<Door_Endurance>10000</Door_Endurance>
<DetectSecretDoor_Lv>0</DetectSecretDoor_Lv>
<UnlockDoor_Lv>0</UnlockDoor_Lv>
<RecoveryTime>30</RecoveryTime>
<isMortalObject>1</isMortalObject>
<DisarmTrap_Lv>0</DisarmTrap_Lv>
<DetectTrap_Lv>0</DetectTrap_Lv>
<TrapID1>65535</TrapID1>
<TrapID2>65535</TrapID2>
<isSecretDungeonEntrance>0</isSecretDungeonEntrance>
</AreaExpansion>
</Area>
<Area id="aUid31">
<AreaUID>31</AreaUID>
<AreaName>29</AreaName>
<AreaType>2</AreaType>
<AccessMap></AccessMap>
<AccessMapName></AccessMapName>
<AreaPos_X>374.43</AreaPos_X>
<AreaPos_X2>387.95</AreaPos_X2>
<AreaPos_Y>112.61</AreaPos_Y>
<AreaPos_Y2>123.75</AreaPos_Y2>
<AreaExpansion>
<Door_Endurance>10000</Door_Endurance>
<DetectSecretDoor_Lv>0</DetectSecretDoor_Lv>
<UnlockDoor_Lv>0</UnlockDoor_Lv>
<RecoveryTime>30</RecoveryTime>
<isMortalObject>1</isMortalObject>
<DisarmTrap_Lv>0</DisarmTrap_Lv>
<DetectTrap_Lv>0</DetectTrap_Lv>
<TrapID1>65535</TrapID1>
<TrapID2>65535</TrapID2>
<isSecretDungeonEntrance>0</isSecretDungeonEntrance>
</AreaExpansion>
</Area>
<Area id="aUid32">
<AreaUID>32</AreaUID>
<AreaName>30</AreaName>
<AreaType>2</AreaType>
<AccessMap></AccessMap>
<AccessMapName></AccessMapName>
<AreaPos_X>348.86</AreaPos_X>
<AreaPos_X2>363.86</AreaPos_X2>
<AreaPos_Y>43.64</AreaPos_Y>
<AreaPos_Y2>55.45</AreaPos_Y2>
<AreaExpansion>
<Door_Endurance>10000</Door_Endurance>
<DetectSecretDoor_Lv>0</DetectSecretDoor_Lv>
<UnlockDoor_Lv>0</UnlockDoor_Lv>
<RecoveryTime>30</RecoveryTime>
<isMortalObject>1</isMortalObject>
<DisarmTrap_Lv>0</DisarmTrap_Lv>
<DetectTrap_Lv>0</DetectTrap_Lv>
<TrapID1>65535</TrapID1>
<TrapID2>65535</TrapID2>
<isSecretDungeonEntrance>0</isSecretDungeonEntrance>
</AreaExpansion>
</Area>
<Area id="aUid33">
<AreaUID>33</AreaUID>
<AreaName>31</AreaName>
<AreaType>2</AreaType>
<AccessMap></AccessMap>
<AccessMapName></AccessMapName>
<AreaPos_X>379.32</AreaPos_X>
<AreaPos_X2>393.86</AreaPos_X2>
<AreaPos_Y>33.64</AreaPos_Y>
<AreaPos_Y2>43.98</AreaPos_Y2>
<AreaExpansion>
<Door_Endurance>10000</Door_Endurance>
<DetectSecretDoor_Lv>0</DetectSecretDoor_Lv>
<UnlockDoor_Lv>0</UnlockDoor_Lv>
<RecoveryTime>30</RecoveryTime>
<isMortalObject>1</isMortalObject>
<DisarmTrap_Lv>0</DisarmTrap_Lv>
<DetectTrap_Lv>0</DetectTrap_Lv>
<TrapID1>65535</TrapID1>
<TrapID2>65535</TrapID2>
<isSecretDungeonEntrance>0</isSecretDungeonEntrance>
</AreaExpansion>
</Area>
<Area id="aUid34">
<AreaUID>34</AreaUID>
<AreaName>32</AreaName>
<AreaType>2</AreaType>
<AccessMap></AccessMap>
<AccessMapName></AccessMapName>
<AreaPos_X>364.32</AreaPos_X>
<AreaPos_X2>376.25</AreaPos_X2>
<AreaPos_Y>4.66</AreaPos_Y>
<AreaPos_Y2>16.36</AreaPos_Y2>
<AreaExpansion>
<Door_Endurance>10000</Door_Endurance>
<DetectSecretDoor_Lv>0</DetectSecretDoor_Lv>
<UnlockDoor_Lv>0</UnlockDoor_Lv>
<RecoveryTime>30</RecoveryTime>
<isMortalObject>1</isMortalObject>
<DisarmTrap_Lv>0</DisarmTrap_Lv>
<DetectTrap_Lv>0</DetectTrap_Lv>
<TrapID1>65535</TrapID1>
<TrapID2>65535</TrapID2>
<isSecretDungeonEntrance>0</isSecretDungeonEntrance>
</AreaExpansion>
</Area>
<Area id="aUid35">
<AreaUID>35</AreaUID>
<AreaName>33</AreaName>
<AreaType>2</AreaType>
<AccessMap></AccessMap>
<AccessMapName></AccessMapName>
<AreaPos_X>338.52</AreaPos_X>
<AreaPos_X2>350.80</AreaPos_X2>
<AreaPos_Y>8.18</AreaPos_Y>
<AreaPos_Y2>16.82</AreaPos_Y2>
<AreaExpansion>
<Door_Endurance>10000</Door_Endurance>
<DetectSecretDoor_Lv>0</DetectSecretDoor_Lv>
<UnlockDoor_Lv>0</UnlockDoor_Lv>
<RecoveryTime>30</RecoveryTime>
<isMortalObject>1</isMortalObject>
<DisarmTrap_Lv>0</DisarmTrap_Lv>
<DetectTrap_Lv>0</DetectTrap_Lv>
<TrapID1>65535</TrapID1>
<TrapID2>65535</TrapID2>
<isSecretDungeonEntrance>0</isSecretDungeonEntrance>
</AreaExpansion>
</Area>
<Area id="aUid36">
<AreaUID>36</AreaUID>
<AreaName>Area 35</AreaName>
<AreaType>4</AreaType>
<AccessMap></AccessMap>
<AccessMapName></AccessMapName>
<AreaPos_X>19.72</AreaPos_X>
<AreaPos_X2>46.93</AreaPos_X2>
<AreaPos_Y>41.42</AreaPos_Y>
<AreaPos_Y2>68.98</AreaPos_Y2>
<AreaExpansion>
</AreaExpansion>
</Area>
<Area id="aUid37">
<AreaUID>37</AreaUID>
<AreaName>Area 36</AreaName>
<AreaType>4</AreaType>
<AccessMap></AccessMap>
<AccessMapName></AccessMapName>
<AreaPos_X>96.76</AreaPos_X>
<AreaPos_X2>120.23</AreaPos_X2>
<AreaPos_Y>40.68</AreaPos_Y>
<AreaPos_Y2>69.26</AreaPos_Y2>
<AreaExpansion>
</AreaExpansion>
</Area>
<Area id="aUid38">
<AreaUID>38</AreaUID>
<AreaName>Area 37</AreaName>
<AreaType>4</AreaType>
<AccessMap></AccessMap>
<AccessMapName></AccessMapName>
<AreaPos_X>122.73</AreaPos_X>
<AreaPos_X2>167.90</AreaPos_X2>
<AreaPos_Y>8.30</AreaPos_Y>
<AreaPos_Y2>27.84</AreaPos_Y2>
<AreaExpansion>
</AreaExpansion>
</Area>
<Area id="aUid39">
<AreaUID>39</AreaUID>
<AreaName>Area 38</AreaName>
<AreaType>4</AreaType>
<AccessMap></AccessMap>
<AccessMapName></AccessMapName>
<AreaPos_X>47.84</AreaPos_X>
<AreaPos_X2>85.06</AreaPos_X2>
<AreaPos_Y>105.00</AreaPos_Y>
<AreaPos_Y2>147.84</AreaPos_Y2>
<AreaExpansion>
</AreaExpansion>
</Area>
<Area id="aUid40">
<AreaUID>40</AreaUID>
<AreaName>Area 39</AreaName>
<AreaType>4</AreaType>
<AccessMap></AccessMap>
<AccessMapName></AccessMapName>
<AreaPos_X>7.61</AreaPos_X>
<AreaPos_X2>27.10</AreaPos_X2>
<AreaPos_Y>161.02</AreaPos_Y>
<AreaPos_Y2>188.64</AreaPos_Y2>
<AreaExpansion>
</AreaExpansion>
</Area>
<Area id="aUid41">
<AreaUID>41</AreaUID>
<AreaName>Area 40</AreaName>
<AreaType>4</AreaType>
<AccessMap></AccessMap>
<AccessMapName></AccessMapName>
<AreaPos_X>41.65</AreaPos_X>
<AreaPos_X2>69.43</AreaPos_X2>
<AreaPos_Y>172.84</AreaPos_Y>
<AreaPos_Y2>194.89</AreaPos_Y2>
<AreaExpansion>
</AreaExpansion>
</Area>
<Area id="aUid42">
<AreaUID>42</AreaUID>
<AreaName>Area 41</AreaName>
<AreaType>4</AreaType>
<AccessMap></AccessMap>
<AccessMapName></AccessMapName>
<AreaPos_X>136.42</AreaPos_X>
<AreaPos_X2>160.28</AreaPos_X2>
<AreaPos_Y>54.20</AreaPos_Y>
<AreaPos_Y2>77.73</AreaPos_Y2>
<AreaExpansion>
</AreaExpansion>
</Area>
<Area id="aUid43">
<AreaUID>43</AreaUID>
<AreaName>Area 42</AreaName>
<AreaType>4</AreaType>
<AccessMap></AccessMap>
<AccessMapName></AccessMapName>
<AreaPos_X>112.73</AreaPos_X>
<AreaPos_X2>133.98</AreaPos_X2>
<AreaPos_Y>126.02</AreaPos_Y>
<AreaPos_Y2>157.95</AreaPos_Y2>
<AreaExpansion>
</AreaExpansion>
</Area>
<Area id="aUid44">
<AreaUID>44</AreaUID>
<AreaName>Area 43</AreaName>
<AreaType>4</AreaType>
<AccessMap></AccessMap>
<AccessMapName></AccessMapName>
<AreaPos_X>210.68</AreaPos_X>
<AreaPos_X2>225.80</AreaPos_X2>
<AreaPos_Y>66.02</AreaPos_Y>
<AreaPos_Y2>94.20</AreaPos_Y2>
<AreaExpansion>
</AreaExpansion>
</Area>
<Area id="aUid45">
<AreaUID>45</AreaUID>
<AreaName>Area 44</AreaName>
<AreaType>4</AreaType>
<AccessMap></AccessMap>
<AccessMapName></AccessMapName>
<AreaPos_X>242.73</AreaPos_X>
<AreaPos_X2>272.39</AreaPos_X2>
<AreaPos_Y>7.61</AreaPos_Y>
<AreaPos_Y2>29.32</AreaPos_Y2>
<AreaExpansion>
</AreaExpansion>
</Area>
<Area id="aUid46">
<AreaUID>46</AreaUID>
<AreaName>Area 45</AreaName>
<AreaType>4</AreaType>
<AccessMap></AccessMap>
<AccessMapName></AccessMapName>
<AreaPos_X>304.43</AreaPos_X>
<AreaPos_X2>335.34</AreaPos_X2>
<AreaPos_Y>60.91</AreaPos_Y>
<AreaPos_Y2>83.30</AreaPos_Y2>
<AreaExpansion>
</AreaExpansion>
</Area>
<Area id="aUid47">
<AreaUID>47</AreaUID>
<AreaName>Area 46</AreaName>
<AreaType>4</AreaType>
<AccessMap></AccessMap>
<AccessMapName></AccessMapName>
<AreaPos_X>253.64</AreaPos_X>
<AreaPos_X2>280.34</AreaPos_X2>
<AreaPos_Y>152.73</AreaPos_Y>
<AreaPos_Y2>170.45</AreaPos_Y2>
<AreaExpansion>
</AreaExpansion>
</Area>
<Area id="aUid48">
<AreaUID>48</AreaUID>
<AreaName>Area 47</AreaName>
<AreaType>4</AreaType>
<AccessMap></AccessMap>
<AccessMapName></AccessMapName>
<AreaPos_X>367.61</AreaPos_X>
<AreaPos_X2>397.67</AreaPos_X2>
<AreaPos_Y>162.27</AreaPos_Y>
<AreaPos_Y2>189.60</AreaPos_Y2>
<AreaExpansion>
</AreaExpansion>
</Area>
<Area id="aUid49">
<AreaUID>49</AreaUID>
<AreaName>Area 48</AreaName>
<AreaType>4</AreaType>
<AccessMap></AccessMap>
<AccessMapName></AccessMapName>
<AreaPos_X>299.55</AreaPos_X>
<AreaPos_X2>332.22</AreaPos_X2>
<AreaPos_Y>175.45</AreaPos_Y>
<AreaPos_Y2>197.27</AreaPos_Y2>
<AreaExpansion>
</AreaExpansion>
</Area>
<Area id="aUid50">
<AreaUID>50</AreaUID>
<AreaName>Area 49</AreaName>
<AreaType>13</AreaType>
<AccessMap></AccessMap>
<AccessMapName></AccessMapName>
<AreaPos_X>321.31</AreaPos_X>
<AreaPos_X2>324.60</AreaPos_X2>
<AreaPos_Y>131.25</AreaPos_Y>
<AreaPos_Y2>133.07</AreaPos_Y2>
<AreaExpansion>
</AreaExpansion>
</Area>
<Area id="aUid51">
<AreaUID>51</AreaUID>
<AreaName>Area 50</AreaName>
<AreaType>4</AreaType>
<AccessMap></AccessMap>
<AccessMapName></AccessMapName>
<AreaPos_X>360.23</AreaPos_X>
<AreaPos_X2>383.18</AreaPos_X2>
<AreaPos_Y>17.95</AreaPos_Y>
<AreaPos_Y2>49.66</AreaPos_Y2>
<AreaExpansion>
</AreaExpansion>
</Area>
<Area id="aUid52">
<AreaUID>52</AreaUID>
<AreaName>Area 51</AreaName>
<AreaType>4</AreaType>
<AccessMap></AccessMap>
<AccessMapName></AccessMapName>
<AreaPos_X>294.20</AreaPos_X>
<AreaPos_X2>310.23</AreaPos_X2>
<AreaPos_Y>39.66</AreaPos_Y>
<AreaPos_Y2>67.27</AreaPos_Y2>
<AreaExpansion>
</AreaExpansion>
</Area>
<Area id="aUid53">
<AreaUID>53</AreaUID>
<AreaName>Area 52</AreaName>
<AreaType>4</AreaType>
<AccessMap></AccessMap>
<AccessMapName></AccessMapName>
<AreaPos_X>189.89</AreaPos_X>
<AreaPos_X2>215.00</AreaPos_X2>
<AreaPos_Y>38.98</AreaPos_Y>
<AreaPos_Y2>62.22</AreaPos_Y2>
<AreaExpansion>
</AreaExpansion>
</Area>
<Area id="aUid54">
<AreaUID>54</AreaUID>
<AreaName>Area 53</AreaName>
<AreaType>4</AreaType>
<AccessMap></AccessMap>
<AccessMapName></AccessMapName>
<AreaPos_X>185.85</AreaPos_X>
<AreaPos_X2>232.44</AreaPos_X2>
<AreaPos_Y>4.26</AreaPos_Y>
<AreaPos_Y2>23.30</AreaPos_Y2>
<AreaExpansion>
</AreaExpansion>
</Area>
<Area id="aUid55">
<AreaUID>55</AreaUID>
<AreaName>Area 54</AreaName>
<AreaType>4</AreaType>
<AccessMap></AccessMap>
<AccessMapName></AccessMapName>
<AreaPos_X>174.32</AreaPos_X>
<AreaPos_X2>197.56</AreaPos_X2>
<AreaPos_Y>162.16</AreaPos_Y>
<AreaPos_Y2>191.65</AreaPos_Y2>
<AreaExpansion>
</AreaExpansion>
</Area>
<Area id="aUid56">
<AreaUID>56</AreaUID>
<AreaName>Area 55</AreaName>
<AreaType>4</AreaType>
<AccessMap></AccessMap>
<AccessMapName></AccessMapName>
<AreaPos_X>225.85</AreaPos_X>
<AreaPos_X2>253.47</AreaPos_X2>
<AreaPos_Y>111.48</AreaPos_Y>
<AreaPos_Y2>136.99</AreaPos_Y2>
<AreaExpansion>
</AreaExpansion>
</Area>
<Area id="aUid57">
<AreaUID>57</AreaUID>
<AreaName>Area 56</AreaName>
<AreaType>4</AreaType>
<AccessMap></AccessMap>
<AccessMapName></AccessMapName>
<AreaPos_X>7.39</AreaPos_X>
<AreaPos_X2>23.41</AreaPos_X2>
<AreaPos_Y>14.49</AreaPos_Y>
<AreaPos_Y2>33.92</AreaPos_Y2>
<AreaExpansion>
</AreaExpansion>
</Area>
<Area id="aUid58">
<AreaUID>58</AreaUID>
<AreaName>Area 57</AreaName>
<AreaType>4</AreaType>
<AccessMap></AccessMap>
<AccessMapName></AccessMapName>
<AreaPos_X>290.17</AreaPos_X>
<AreaPos_X2>311.42</AreaPos_X2>
<AreaPos_Y>130.91</AreaPos_Y>
<AreaPos_Y2>170.40</AreaPos_Y2>
<AreaExpansion>
</AreaExpansion>
</Area>
<Area id="aUid59">
<AreaUID>59</AreaUID>
<AreaName>Area 58</AreaName>
<AreaType>4</AreaType>
<AccessMap></AccessMap>
<AccessMapName></AccessMapName>
<AreaPos_X>296.25</AreaPos_X>
<AreaPos_X2>316.99</AreaPos_X2>
<AreaPos_Y>89.09</AreaPos_Y>
<AreaPos_Y2>112.16</AreaPos_Y2>
<AreaExpansion>
</AreaExpansion>
</Area>
<Area id="aUid60">
<AreaUID>60</AreaUID>
<AreaName>Area 59</AreaName>
<AreaType>4</AreaType>
<AccessMap></AccessMap>
<AccessMapName></AccessMapName>
<AreaPos_X>48.41</AreaPos_X>
<AreaPos_X2>80.45</AreaPos_X2>
<AreaPos_Y>65.28</AreaPos_Y>
<AreaPos_Y2>86.82</AreaPos_Y2>
<AreaExpansion>
</AreaExpansion>
</Area>
<Area id="aUid61">
<AreaUID>61</AreaUID>
<AreaName>Area 60</AreaName>
<AreaType>4</AreaType>
<AccessMap></AccessMap>
<AccessMapName></AccessMapName>
<AreaPos_X>46.25</AreaPos_X>
<AreaPos_X2>77.67</AreaPos_X2>
<AreaPos_Y>9.38</AreaPos_Y>
<AreaPos_Y2>29.32</AreaPos_Y2>
<AreaExpansion>
</AreaExpansion>
</Area>
<Area id="aUid62">
<AreaUID>62</AreaUID>
<AreaName>Area 61</AreaName>
<AreaType>4</AreaType>
<AccessMap></AccessMap>
<AccessMapName></AccessMapName>
<AreaPos_X>120.74</AreaPos_X>
<AreaPos_X2>156.08</AreaPos_X2>
<AreaPos_Y>174.55</AreaPos_Y>
<AreaPos_Y2>194.66</AreaPos_Y2>
<AreaExpansion>
</AreaExpansion>
</Area>
<Area id="aUid64">
<AreaUID>64</AreaUID>
<AreaName>Area 63</AreaName>
<AreaType>11</AreaType>
<AccessMap></AccessMap>
<AccessMapName></AccessMapName>
<AreaPos_X>61.82</AreaPos_X>
<AreaPos_X2>76.19</AreaPos_X2>
<AreaPos_Y>43.81</AreaPos_Y>
<AreaPos_Y2>54.38</AreaPos_Y2>
<AreaExpansion>
<RecoveryTime>600</RecoveryTime>
<DetectTrap_Lv>10</DetectTrap_Lv>
<DisarmTrap_Lv>4</DisarmTrap_Lv>
<TrapID1>1</TrapID1>
<TrapID2>65535</TrapID2>
</AreaExpansion>
</Area>
<Area id="aUid65">
<AreaUID>65</AreaUID>
<AreaName>Area 64</AreaName>
<AreaType>11</AreaType>
<AccessMap></AccessMap>
<AccessMapName></AccessMapName>
<AreaPos_X>167.44</AreaPos_X>
<AreaPos_X2>178.41</AreaPos_X2>
<AreaPos_Y>136.25</AreaPos_Y>
<AreaPos_Y2>147.22</AreaPos_Y2>
<AreaExpansion>
<RecoveryTime>600</RecoveryTime>
<DetectTrap_Lv>4</DetectTrap_Lv>
<DisarmTrap_Lv>5</DisarmTrap_Lv>
<TrapID1>22</TrapID1>
<TrapID2>65535</TrapID2>
</AreaExpansion>
</Area>
<Area id="aUid66">
<AreaUID>66</AreaUID>
<AreaName>Area 65</AreaName>
<AreaType>11</AreaType>
<AccessMap></AccessMap>
<AccessMapName></AccessMapName>
<AreaPos_X>32.73</AreaPos_X>
<AreaPos_X2>47.27</AreaPos_X2>
<AreaPos_Y>16.59</AreaPos_Y>
<AreaPos_Y2>25.23</AreaPos_Y2>
<AreaExpansion>
<RecoveryTime>600</RecoveryTime>
<DetectTrap_Lv>2</DetectTrap_Lv>
<DisarmTrap_Lv>4</DisarmTrap_Lv>
<TrapID1>33</TrapID1>
<TrapID2>65535</TrapID2>
</AreaExpansion>
</Area>
<Area id="aUid67">
<AreaUID>67</AreaUID>
<AreaName>Area 66</AreaName>
<AreaType>11</AreaType>
<AccessMap></AccessMap>
<AccessMapName></AccessMapName>
<AreaPos_X>105.57</AreaPos_X>
<AreaPos_X2>112.67</AreaPos_X2>
<AreaPos_Y>25.63</AreaPos_Y>
<AreaPos_Y2>36.42</AreaPos_Y2>
<AreaExpansion>
<RecoveryTime>600</RecoveryTime>
<DetectTrap_Lv>2</DetectTrap_Lv>
<DisarmTrap_Lv>4</DisarmTrap_Lv>
<TrapID1>28</TrapID1>
<TrapID2>65535</TrapID2>
</AreaExpansion>
</Area>
<Area id="aUid68">
<AreaUID>68</AreaUID>
<AreaName>Area 67</AreaName>
<AreaType>11</AreaType>
<AccessMap></AccessMap>
<AccessMapName></AccessMapName>
<AreaPos_X>131.02</AreaPos_X>
<AreaPos_X2>156.59</AreaPos_X2>
<AreaPos_Y>12.84</AreaPos_Y>
<AreaPos_Y2>27.39</AreaPos_Y2>
<AreaExpansion>
<RecoveryTime>600</RecoveryTime>
<DetectTrap_Lv>5</DetectTrap_Lv>
<DisarmTrap_Lv>4</DisarmTrap_Lv>
<TrapID1>10</TrapID1>
<TrapID2>65535</TrapID2>
</AreaExpansion>
</Area>
<Area id="aUid69">
<AreaUID>69</AreaUID>
<AreaName>Area 68</AreaName>
<AreaType>11</AreaType>
<AccessMap></AccessMap>
<AccessMapName></AccessMapName>
<AreaPos_X>225.63</AreaPos_X>
<AreaPos_X2>247.27</AreaPos_X2>
<AreaPos_Y>11.08</AreaPos_Y>
<AreaPos_Y2>23.64</AreaPos_Y2>
<AreaExpansion>
<RecoveryTime>600</RecoveryTime>
<DetectTrap_Lv>10</DetectTrap_Lv>
<DisarmTrap_Lv>6</DisarmTrap_Lv>
<TrapID1>19</TrapID1>
<TrapID2>65535</TrapID2>
</AreaExpansion>
</Area>
<Area id="aUid70">
<AreaUID>70</AreaUID>
<AreaName>Area 69</AreaName>
<AreaType>11</AreaType>
<AccessMap></AccessMap>
<AccessMapName></AccessMapName>
<AreaPos_X>316.19</AreaPos_X>
<AreaPos_X2>327.22</AreaPos_X2>
<AreaPos_Y>12.73</AreaPos_Y>
<AreaPos_Y2>20.17</AreaPos_Y2>
<AreaExpansion>
<RecoveryTime>600</RecoveryTime>
<DetectTrap_Lv>15</DetectTrap_Lv>
<DisarmTrap_Lv>15</DisarmTrap_Lv>
<TrapID1>32</TrapID1>
<TrapID2>65535</TrapID2>
</AreaExpansion>
</Area>
<Area id="aUid71">
<AreaUID>71</AreaUID>
<AreaName>Area 70</AreaName>
<AreaType>11</AreaType>
<AccessMap></AccessMap>
<AccessMapName></AccessMapName>
<AreaPos_X>363.75</AreaPos_X>
<AreaPos_X2>381.93</AreaPos_X2>
<AreaPos_Y>27.33</AreaPos_Y>
<AreaPos_Y2>36.25</AreaPos_Y2>
<AreaExpansion>
<RecoveryTime>600</RecoveryTime>
<DetectTrap_Lv>15</DetectTrap_Lv>
<DisarmTrap_Lv>15</DisarmTrap_Lv>
<TrapID1>20</TrapID1>
<TrapID2>65535</TrapID2>
</AreaExpansion>
</Area>
<Area id="aUid72">
<AreaUID>72</AreaUID>
<AreaName>Area 71</AreaName>
<AreaType>11</AreaType>
<AccessMap></AccessMap>
<AccessMapName></AccessMapName>
<AreaPos_X>348.75</AreaPos_X>
<AreaPos_X2>359.77</AreaPos_X2>
<AreaPos_Y>56.48</AreaPos_Y>
<AreaPos_Y2>67.33</AreaPos_Y2>
<AreaExpansion>
<RecoveryTime>600</RecoveryTime>
<DetectTrap_Lv>15</DetectTrap_Lv>
<DisarmTrap_Lv>15</DisarmTrap_Lv>
<TrapID1>30</TrapID1>
<TrapID2>65535</TrapID2>
</AreaExpansion>
</Area>
<Area id="aUid73">
<AreaUID>73</AreaUID>
<AreaName>Area 72</AreaName>
<AreaType>11</AreaType>
<AccessMap></AccessMap>
<AccessMapName></AccessMapName>
<AreaPos_X>293.98</AreaPos_X>
<AreaPos_X2>309.26</AreaPos_X2>
<AreaPos_Y>47.39</AreaPos_Y>
<AreaPos_Y2>60.00</AreaPos_Y2>
<AreaExpansion>
<RecoveryTime>600</RecoveryTime>
<DetectTrap_Lv>15</DetectTrap_Lv>
<DisarmTrap_Lv>15</DisarmTrap_Lv>
<TrapID1>34</TrapID1>
<TrapID2>65535</TrapID2>
</AreaExpansion>
</Area>
<Area id="aUid74">
<AreaUID>74</AreaUID>
<AreaName>Area 73</AreaName>
<AreaType>11</AreaType>
<AccessMap></AccessMap>
<AccessMapName></AccessMapName>
<AreaPos_X>301.93</AreaPos_X>
<AreaPos_X2>320.11</AreaPos_X2>
<AreaPos_Y>85.51</AreaPos_Y>
<AreaPos_Y2>92.67</AreaPos_Y2>
<AreaExpansion>
<RecoveryTime>600</RecoveryTime>
<DetectTrap_Lv>15</DetectTrap_Lv>
<DisarmTrap_Lv>15</DisarmTrap_Lv>
<TrapID1>3</TrapID1>
<TrapID2>65535</TrapID2>
</AreaExpansion>
</Area>
<Area id="aUid75">
<AreaUID>75</AreaUID>
<AreaName>Area 74</AreaName>
<AreaType>11</AreaType>
<AccessMap></AccessMap>
<AccessMapName></AccessMapName>
<AreaPos_X>254.60</AreaPos_X>
<AreaPos_X2>272.95</AreaPos_X2>
<AreaPos_Y>67.16</AreaPos_Y>
<AreaPos_Y2>78.07</AreaPos_Y2>
<AreaExpansion>
<RecoveryTime>600</RecoveryTime>
<DetectTrap_Lv>15</DetectTrap_Lv>
<DisarmTrap_Lv>15</DisarmTrap_Lv>
<TrapID1>24</TrapID1>
<TrapID2>65535</TrapID2>
</AreaExpansion>
</Area>
<Area id="aUid76">
<AreaUID>76</AreaUID>
<AreaName>Area 75</AreaName>
<AreaType>11</AreaType>
<AccessMap></AccessMap>
<AccessMapName></AccessMapName>
<AreaPos_X>192.73</AreaPos_X>
<AreaPos_X2>214.72</AreaPos_X2>
<AreaPos_Y>47.05</AreaPos_Y>
<AreaPos_Y2>59.94</AreaPos_Y2>
<AreaExpansion>
<RecoveryTime>600</RecoveryTime>
<DetectTrap_Lv>15</DetectTrap_Lv>
<DisarmTrap_Lv>15</DisarmTrap_Lv>
<TrapID1>27</TrapID1>
<TrapID2>65535</TrapID2>
</AreaExpansion>
</Area>
<Area id="aUid77">
<AreaUID>77</AreaUID>
<AreaName>Area 76</AreaName>
<AreaType>11</AreaType>
<AccessMap></AccessMap>
<AccessMapName></AccessMapName>
<AreaPos_X>138.47</AreaPos_X>
<AreaPos_X2>160.06</AreaPos_X2>
<AreaPos_Y>51.42</AreaPos_Y>
<AreaPos_Y2>67.10</AreaPos_Y2>
<AreaExpansion>
<RecoveryTime>600</RecoveryTime>
<DetectTrap_Lv>15</DetectTrap_Lv>
<DisarmTrap_Lv>15</DisarmTrap_Lv>
<TrapID1>31</TrapID1>
<TrapID2>65535</TrapID2>
</AreaExpansion>
</Area>
<Area id="aUid78">
<AreaUID>78</AreaUID>
<AreaName>Area 77</AreaName>
<AreaType>11</AreaType>
<AccessMap></AccessMap>
<AccessMapName></AccessMapName>
<AreaPos_X>22.10</AreaPos_X>
<AreaPos_X2>50.74</AreaPos_X2>
<AreaPos_Y>61.99</AreaPos_Y>
<AreaPos_Y2>74.26</AreaPos_Y2>
<AreaExpansion>
<RecoveryTime>600</RecoveryTime>
<DetectTrap_Lv>15</DetectTrap_Lv>
<DisarmTrap_Lv>15</DisarmTrap_Lv>
<TrapID1>29</TrapID1>
<TrapID2>65535</TrapID2>
</AreaExpansion>
</Area>
<Area id="aUid79">
<AreaUID>79</AreaUID>
<AreaName>Area 78</AreaName>
<AreaType>11</AreaType>
<AccessMap></AccessMap>
<AccessMapName></AccessMapName>
<AreaPos_X>11.02</AreaPos_X>
<AreaPos_X2>25.45</AreaPos_X2>
<AreaPos_Y>94.49</AreaPos_Y>
<AreaPos_Y2>106.99</AreaPos_Y2>
<AreaExpansion>
<RecoveryTime>600</RecoveryTime>
<DetectTrap_Lv>15</DetectTrap_Lv>
<DisarmTrap_Lv>15</DisarmTrap_Lv>
<TrapID1>30</TrapID1>
<TrapID2>65535</TrapID2>
</AreaExpansion>
</Area>
<Area id="aUid80">
<AreaUID>80</AreaUID>
<AreaName>Area 79</AreaName>
<AreaType>11</AreaType>
<AccessMap></AccessMap>
<AccessMapName></AccessMapName>
<AreaPos_X>91.19</AreaPos_X>
<AreaPos_X2>105.34</AreaPos_X2>
<AreaPos_Y>107.50</AreaPos_Y>
<AreaPos_Y2>116.31</AreaPos_Y2>
<AreaExpansion>
<RecoveryTime>600</RecoveryTime>
<DetectTrap_Lv>15</DetectTrap_Lv>
<DisarmTrap_Lv>15</DisarmTrap_Lv>
<TrapID1>10</TrapID1>
<TrapID2>65535</TrapID2>
</AreaExpansion>
</Area>
<Area id="aUid81">
<AreaUID>81</AreaUID>
<AreaName>Area 80</AreaName>
<AreaType>11</AreaType>
<AccessMap></AccessMap>
<AccessMapName></AccessMapName>
<AreaPos_X>7.10</AreaPos_X>
<AreaPos_X2>18.18</AreaPos_X2>
<AreaPos_Y>145.40</AreaPos_Y>
<AreaPos_Y2>156.42</AreaPos_Y2>
<AreaExpansion>
<RecoveryTime>600</RecoveryTime>
<DetectTrap_Lv>15</DetectTrap_Lv>
<DisarmTrap_Lv>15</DisarmTrap_Lv>
<TrapID1>1</TrapID1>
<TrapID2>65535</TrapID2>
</AreaExpansion>
</Area>
<Area id="aUid82">
<AreaUID>82</AreaUID>
<AreaName>Area 81</AreaName>
<AreaType>11</AreaType>
<AccessMap></AccessMap>
<AccessMapName></AccessMapName>
<AreaPos_X>58.07</AreaPos_X>
<AreaPos_X2>76.42</AreaPos_X2>
<AreaPos_Y>171.02</AreaPos_Y>
<AreaPos_Y2>183.47</AreaPos_Y2>
<AreaExpansion>
<RecoveryTime>600</RecoveryTime>
<DetectTrap_Lv>15</DetectTrap_Lv>
<DisarmTrap_Lv>15</DisarmTrap_Lv>
<TrapID1>24</TrapID1>
<TrapID2>65535</TrapID2>
</AreaExpansion>
</Area>
<Area id="aUid83">
<AreaUID>83</AreaUID>
<AreaName>Area 82</AreaName>
<AreaType>11</AreaType>
<AccessMap></AccessMap>
<AccessMapName></AccessMapName>
<AreaPos_X>120.11</AreaPos_X>
<AreaPos_X2>134.83</AreaPos_X2>
<AreaPos_Y>181.88</AreaPos_Y>
<AreaPos_Y2>190.91</AreaPos_Y2>
<AreaExpansion>
<RecoveryTime>600</RecoveryTime>
<DetectTrap_Lv>15</DetectTrap_Lv>
<DisarmTrap_Lv>15</DisarmTrap_Lv>
<TrapID1>2</TrapID1>
<TrapID2>65535</TrapID2>
</AreaExpansion>
</Area>
<Area id="aUid84">
<AreaUID>84</AreaUID>
<AreaName>Area 83</AreaName>
<AreaType>11</AreaType>
<AccessMap></AccessMap>
<AccessMapName></AccessMapName>
<AreaPos_X>123.69</AreaPos_X>
<AreaPos_X2>141.76</AreaPos_X2>
<AreaPos_Y>123.75</AreaPos_Y>
<AreaPos_Y2>134.66</AreaPos_Y2>
<AreaExpansion>
<RecoveryTime>600</RecoveryTime>
<DetectTrap_Lv>15</DetectTrap_Lv>
<DisarmTrap_Lv>15</DisarmTrap_Lv>
<TrapID1>29</TrapID1>
<TrapID2>65535</TrapID2>
</AreaExpansion>
</Area>
<Area id="aUid85">
<AreaUID>85</AreaUID>
<AreaName>Area 84</AreaName>
<AreaType>11</AreaType>
<AccessMap></AccessMap>
<AccessMapName></AccessMapName>
<AreaPos_X>87.27</AreaPos_X>
<AreaPos_X2>105.51</AreaPos_X2>
<AreaPos_Y>67.27</AreaPos_Y>
<AreaPos_Y2>76.25</AreaPos_Y2>
<AreaExpansion>
<RecoveryTime>600</RecoveryTime>
<DetectTrap_Lv>15</DetectTrap_Lv>
<DisarmTrap_Lv>15</DisarmTrap_Lv>
<TrapID1>30</TrapID1>
<TrapID2>65535</TrapID2>
</AreaExpansion>
</Area>
<Area id="aUid86">
<AreaUID>86</AreaUID>
<AreaName>Area 85</AreaName>
<AreaType>11</AreaType>
<AccessMap></AccessMap>
<AccessMapName></AccessMapName>
<AreaPos_X>36.36</AreaPos_X>
<AreaPos_X2>50.91</AreaPos_X2>
<AreaPos_Y>127.10</AreaPos_Y>
<AreaPos_Y2>136.53</AreaPos_Y2>
<AreaExpansion>
<RecoveryTime>600</RecoveryTime>
<DetectTrap_Lv>15</DetectTrap_Lv>
<DisarmTrap_Lv>15</DisarmTrap_Lv>
<TrapID1>5</TrapID1>
<TrapID2>65535</TrapID2>
</AreaExpansion>
</Area>
<Area id="aUid87">
<AreaUID>87</AreaUID>
<AreaName>Area 86</AreaName>
<AreaType>11</AreaType>
<AccessMap></AccessMap>
<AccessMapName></AccessMapName>
<AreaPos_X>276.36</AreaPos_X>
<AreaPos_X2>291.08</AreaPos_X2>
<AreaPos_Y>121.82</AreaPos_Y>
<AreaPos_Y2>132.50</AreaPos_Y2>
<AreaExpansion>
<RecoveryTime>600</RecoveryTime>
<DetectTrap_Lv>15</DetectTrap_Lv>
<DisarmTrap_Lv>15</DisarmTrap_Lv>
<TrapID1>28</TrapID1>
<TrapID2>65535</TrapID2>
</AreaExpansion>
</Area>
<Area id="aUid88">
<AreaUID>88</AreaUID>
<AreaName>Area 87</AreaName>
<AreaType>11</AreaType>
<AccessMap></AccessMap>
<AccessMapName></AccessMapName>
<AreaPos_X>145.57</AreaPos_X>
<AreaPos_X2>163.64</AreaPos_X2>
<AreaPos_Y>163.58</AreaPos_Y>
<AreaPos_Y2>176.25</AreaPos_Y2>
<AreaExpansion>
<RecoveryTime>600</RecoveryTime>
<DetectTrap_Lv>15</DetectTrap_Lv>
<DisarmTrap_Lv>15</DisarmTrap_Lv>
<TrapID1>33</TrapID1>
<TrapID2>65535</TrapID2>
</AreaExpansion>
</Area>
<Area id="aUid89">
<AreaUID>89</AreaUID>
<AreaName>Area 88</AreaName>
<AreaType>11</AreaType>
<AccessMap></AccessMap>
<AccessMapName></AccessMapName>
<AreaPos_X>189.32</AreaPos_X>
<AreaPos_X2>203.75</AreaPos_X2>
<AreaPos_Y>156.42</AreaPos_Y>
<AreaPos_Y2>167.22</AreaPos_Y2>
<AreaExpansion>
<RecoveryTime>600</RecoveryTime>
<DetectTrap_Lv>15</DetectTrap_Lv>
<DisarmTrap_Lv>15</DisarmTrap_Lv>
<TrapID1>22</TrapID1>
<TrapID2>65535</TrapID2>
</AreaExpansion>
</Area>
<Area id="aUid90">
<AreaUID>90</AreaUID>
<AreaName>Area 89</AreaName>
<AreaType>11</AreaType>
<AccessMap></AccessMap>
<AccessMapName></AccessMapName>
<AreaPos_X>196.31</AreaPos_X>
<AreaPos_X2>221.82</AreaPos_X2>
<AreaPos_Y>109.03</AreaPos_Y>
<AreaPos_Y2>120.00</AreaPos_Y2>
<AreaExpansion>
<RecoveryTime>600</RecoveryTime>
<DetectTrap_Lv>15</DetectTrap_Lv>
<DisarmTrap_Lv>15</DisarmTrap_Lv>
<TrapID1>31</TrapID1>
<TrapID2>65535</TrapID2>
</AreaExpansion>
</Area>
<Area id="aUid91">
<AreaUID>91</AreaUID>
<AreaName>Area 90</AreaName>
<AreaType>11</AreaType>
<AccessMap></AccessMap>
<AccessMapName></AccessMapName>
<AreaPos_X>247.27</AreaPos_X>
<AreaPos_X2>261.76</AreaPos_X2>
<AreaPos_Y>158.24</AreaPos_Y>
<AreaPos_Y2>170.97</AreaPos_Y2>
<AreaExpansion>
<RecoveryTime>600</RecoveryTime>
<DetectTrap_Lv>15</DetectTrap_Lv>
<DisarmTrap_Lv>15</DisarmTrap_Lv>
<TrapID1>27</TrapID1>
<TrapID2>65535</TrapID2>
</AreaExpansion>
</Area>
<Area id="aUid92">
<AreaUID>92</AreaUID>
<AreaName>Area 91</AreaName>
<AreaType>13</AreaType>
<AccessMap></AccessMap>
<AccessMapName></AccessMapName>
<AreaPos_X>334.60</AreaPos_X>
<AreaPos_X2>338.24</AreaPos_X2>
<AreaPos_Y>35.06</AreaPos_Y>
<AreaPos_Y2>37.05</AreaPos_Y2>
<AreaExpansion>
</AreaExpansion>
</Area>
<Area id="aUid93">
<AreaUID>93</AreaUID>
<AreaName>Area 92</AreaName>
<AreaType>13</AreaType>
<AccessMap></AccessMap>
<AccessMapName></AccessMapName>
<AreaPos_X>336.82</AreaPos_X>
<AreaPos_X2>340.57</AreaPos_X2>
<AreaPos_Y>38.75</AreaPos_Y>
<AreaPos_Y2>40.80</AreaPos_Y2>
<AreaExpansion>
</AreaExpansion>
</Area>
<Area id="aUid94">
<AreaUID>94</AreaUID>
<AreaName>Area 93</AreaName>
<AreaType>13</AreaType>
<AccessMap></AccessMap>
<AccessMapName></AccessMapName>
<AreaPos_X>342.10</AreaPos_X>
<AreaPos_X2>346.36</AreaPos_X2>
<AreaPos_Y>35.80</AreaPos_Y>
<AreaPos_Y2>38.07</AreaPos_Y2>
<AreaExpansion>
</AreaExpansion>
</Area>
<Area id="aUid95">
<AreaUID>95</AreaUID>
<AreaName>Area 94</AreaName>
<AreaType>13</AreaType>
<AccessMap></AccessMap>
<AccessMapName></AccessMapName>
<AreaPos_X>331.36</AreaPos_X>
<AreaPos_X2>335.51</AreaPos_X2>
<AreaPos_Y>37.84</AreaPos_Y>
<AreaPos_Y2>39.77</AreaPos_Y2>
<AreaExpansion>
</AreaExpansion>
</Area>
<Area id="aUid96">
<AreaUID>96</AreaUID>
<AreaName>Area 95</AreaName>
<AreaType>13</AreaType>
<AccessMap></AccessMap>
<AccessMapName></AccessMapName>
<AreaPos_X>324.89</AreaPos_X>
<AreaPos_X2>328.92</AreaPos_X2>
<AreaPos_Y>37.16</AreaPos_Y>
<AreaPos_Y2>39.09</AreaPos_Y2>
<AreaExpansion>
</AreaExpansion>
</Area>
<Area id="aUid97">
<AreaUID>97</AreaUID>
<AreaName>Area 96</AreaName>
<AreaType>13</AreaType>
<AccessMap></AccessMap>
<AccessMapName></AccessMapName>
<AreaPos_X>325.11</AreaPos_X>
<AreaPos_X2>328.92</AreaPos_X2>
<AreaPos_Y>40.51</AreaPos_Y>
<AreaPos_Y2>42.73</AreaPos_Y2>
<AreaExpansion>
</AreaExpansion>
</Area>
<Area id="aUid98">
<AreaUID>98</AreaUID>
<AreaName>Area 97</AreaName>
<AreaType>13</AreaType>
<AccessMap></AccessMap>
<AccessMapName></AccessMapName>
<AreaPos_X>319.20</AreaPos_X>
<AreaPos_X2>323.24</AreaPos_X2>
<AreaPos_Y>37.56</AreaPos_Y>
<AreaPos_Y2>39.49</AreaPos_Y2>
<AreaExpansion>
</AreaExpansion>
</Area>
<Area id="aUid99">
<AreaUID>99</AreaUID>
<AreaName>Area 98</AreaName>
<AreaType>13</AreaType>
<AccessMap></AccessMap>
<AccessMapName></AccessMapName>
<AreaPos_X>316.65</AreaPos_X>
<AreaPos_X2>320.45</AreaPos_X2>
<AreaPos_Y>40.97</AreaPos_Y>
<AreaPos_Y2>42.84</AreaPos_Y2>
<AreaExpansion>
</AreaExpansion>
</Area>
<Area id="aUid100">
<AreaUID>100</AreaUID>
<AreaName>Area 99</AreaName>
<AreaType>13</AreaType>
<AccessMap></AccessMap>
<AccessMapName></AccessMapName>
<AreaPos_X>347.16</AreaPos_X>
<AreaPos_X2>350.28</AreaPos_X2>
<AreaPos_Y>109.55</AreaPos_Y>
<AreaPos_Y2>111.65</AreaPos_Y2>
<AreaExpansion>
</AreaExpansion>
</Area>
<Area id="aUid101">
<AreaUID>101</AreaUID>
<AreaName>Area 100</AreaName>
<AreaType>13</AreaType>
<AccessMap></AccessMap>
<AccessMapName></AccessMapName>
<AreaPos_X>352.27</AreaPos_X>
<AreaPos_X2>356.48</AreaPos_X2>
<AreaPos_Y>109.60</AreaPos_Y>
<AreaPos_Y2>111.59</AreaPos_Y2>
<AreaExpansion>
</AreaExpansion>
</Area>
<Area id="aUid102">
<AreaUID>102</AreaUID>
<AreaName>Area 101</AreaName>
<AreaType>13</AreaType>
<AccessMap></AccessMap>
<AccessMapName></AccessMapName>
<AreaPos_X>350.17</AreaPos_X>
<AreaPos_X2>353.75</AreaPos_X2>
<AreaPos_Y>112.95</AreaPos_Y>
<AreaPos_Y2>115.00</AreaPos_Y2>
<AreaExpansion>
</AreaExpansion>
</Area>
<Area id="aUid103">
<AreaUID>103</AreaUID>
<AreaName>Area 102</AreaName>
<AreaType>13</AreaType>
<AccessMap></AccessMap>
<AccessMapName></AccessMapName>
<AreaPos_X>355.34</AreaPos_X>
<AreaPos_X2>358.58</AreaPos_X2>
<AreaPos_Y>113.75</AreaPos_Y>
<AreaPos_Y2>115.45</AreaPos_Y2>
<AreaExpansion>
</AreaExpansion>
</Area>
<Area id="aUid104">
<AreaUID>104</AreaUID>
<AreaName>Area 103</AreaName>
<AreaType>13</AreaType>
<AccessMap></AccessMap>
<AccessMapName></AccessMapName>
<AreaPos_X>350.80</AreaPos_X>
<AreaPos_X2>354.49</AreaPos_X2>
<AreaPos_Y>116.08</AreaPos_Y>
<AreaPos_Y2>117.67</AreaPos_Y2>
<AreaExpansion>
</AreaExpansion>
</Area>
<Area id="aUid105">
<AreaUID>105</AreaUID>
<AreaName>Area 104</AreaName>
<AreaType>13</AreaType>
<AccessMap></AccessMap>
<AccessMapName></AccessMapName>
<AreaPos_X>350.40</AreaPos_X>
<AreaPos_X2>353.69</AreaPos_X2>
<AreaPos_Y>106.42</AreaPos_Y>
<AreaPos_Y2>108.07</AreaPos_Y2>
<AreaExpansion>
</AreaExpansion>
</Area>
<Area id="aUid106">
<AreaUID>106</AreaUID>
<AreaName>Area 105</AreaName>
<AreaType>13</AreaType>
<AccessMap></AccessMap>
<AccessMapName></AccessMapName>
<AreaPos_X>344.77</AreaPos_X>
<AreaPos_X2>347.95</AreaPos_X2>
<AreaPos_Y>106.82</AreaPos_Y>
<AreaPos_Y2>108.41</AreaPos_Y2>
<AreaExpansion>
</AreaExpansion>
</Area>
<Area id="aUid107">
<AreaUID>107</AreaUID>
<AreaName>Area 106</AreaName>
<AreaType>13</AreaType>
<AccessMap></AccessMap>
<AccessMapName></AccessMapName>
<AreaPos_X>325.91</AreaPos_X>
<AreaPos_X2>329.83</AreaPos_X2>
<AreaPos_Y>135.45</AreaPos_Y>
<AreaPos_Y2>137.73</AreaPos_Y2>
<AreaExpansion>
</AreaExpansion>
</Area>
<Area id="aUid108">
<AreaUID>108</AreaUID>
<AreaName>Area 107</AreaName>
<AreaType>13</AreaType>
<AccessMap></AccessMap>
<AccessMapName></AccessMapName>
<AreaPos_X>321.25</AreaPos_X>
<AreaPos_X2>324.72</AreaPos_X2>
<AreaPos_Y>134.09</AreaPos_Y>
<AreaPos_Y2>135.91</AreaPos_Y2>
<AreaExpansion>
</AreaExpansion>
</Area>
<Area id="aUid109">
<AreaUID>109</AreaUID>
<AreaName>Area 108</AreaName>
<AreaType>13</AreaType>
<AccessMap></AccessMap>
<AccessMapName></AccessMapName>
<AreaPos_X>327.22</AreaPos_X>
<AreaPos_X2>330.68</AreaPos_X2>
<AreaPos_Y>131.65</AreaPos_Y>
<AreaPos_Y2>133.52</AreaPos_Y2>
<AreaExpansion>
</AreaExpansion>
</Area>
<Area id="aUid110">
<AreaUID>110</AreaUID>
<AreaName>Area 109</AreaName>
<AreaType>13</AreaType>
<AccessMap></AccessMap>
<AccessMapName></AccessMapName>
<AreaPos_X>320.85</AreaPos_X>
<AreaPos_X2>324.15</AreaPos_X2>
<AreaPos_Y>137.78</AreaPos_Y>
<AreaPos_Y2>139.60</AreaPos_Y2>
<AreaExpansion>
</AreaExpansion>
</Area>
<Area id="aUid111">
<AreaUID>111</AreaUID>
<AreaName>Area 110</AreaName>
<AreaType>13</AreaType>
<AccessMap></AccessMap>
<AccessMapName></AccessMapName>
<AreaPos_X>329.20</AreaPos_X>
<AreaPos_X2>333.30</AreaPos_X2>
<AreaPos_Y>138.01</AreaPos_Y>
<AreaPos_Y2>140.06</AreaPos_Y2>
<AreaExpansion>
</AreaExpansion>
</Area>
<Area id="aUid112">
<AreaUID>112</AreaUID>
<AreaName>Area 111</AreaName>
<AreaType>13</AreaType>
<AccessMap></AccessMap>
<AccessMapName></AccessMapName>
<AreaPos_X>325.28</AreaPos_X>
<AreaPos_X2>328.86</AreaPos_X2>
<AreaPos_Y>138.98</AreaPos_Y>
<AreaPos_Y2>141.08</AreaPos_Y2>
<AreaExpansion>
</AreaExpansion>
</Area>
<Area id="aUid113">
<AreaUID>113</AreaUID>
<AreaName>Area 112</AreaName>
<AreaType>13</AreaType>
<AccessMap></AccessMap>
<AccessMapName></AccessMapName>
<AreaPos_X>321.36</AreaPos_X>
<AreaPos_X2>324.89</AreaPos_X2>
<AreaPos_Y>140.68</AreaPos_Y>
<AreaPos_Y2>142.73</AreaPos_Y2>
<AreaExpansion>
</AreaExpansion>
</Area>
<Area id="aUid114">
<AreaUID>114</AreaUID>
<AreaName>Area 113</AreaName>
<AreaType>13</AreaType>
<AccessMap></AccessMap>
<AccessMapName></AccessMapName>
<AreaPos_X>328.35</AreaPos_X>
<AreaPos_X2>332.22</AreaPos_X2>
<AreaPos_Y>141.70</AreaPos_Y>
<AreaPos_Y2>144.03</AreaPos_Y2>
<AreaExpansion>
</AreaExpansion>
</Area>
<Area id="aUid115">
<AreaUID>115</AreaUID>
<AreaName>Area 114</AreaName>
<AreaType>13</AreaType>
<AccessMap></AccessMap>
<AccessMapName></AccessMapName>
<AreaPos_X>324.38</AreaPos_X>
<AreaPos_X2>327.84</AreaPos_X2>
<AreaPos_Y>143.18</AreaPos_Y>
<AreaPos_Y2>145.11</AreaPos_Y2>
<AreaExpansion>
</AreaExpansion>
</Area>
</AreaData>
</MapData>
