<?xml version="1.0" encoding="utf-8"?>
<MapData>
<Details>
<FileName>[042]M12_M01_B06.rmd</FileName>
<FileType>Red Stone Scenario File 6.1 beta</FileType>
<MapName>廃坑　Ｂ６</MapName>
<SysWidth>120</SysWidth>
<SysHeight>100</SysHeight>
<TgaWidth>240</TgaWidth>
<TgaHeight>100</TgaHeight>
<MapType>1</MapType>
<isPremiumMap>0</isPremiumMap>
<isPvPMap>0</isPvPMap>
<MapView_Lv>0</MapView_Lv>
<isLocationStrage>1</isLocationStrage>
<P_SubElement1>0</P_SubElement1>
<P_SubElement2>0</P_SubElement2>
<P_SubElement3>0</P_SubElement3>
<P_SubElement4>0</P_SubElement4>
<P_SubElement5>0</P_SubElement5>
<P_SubElement6>0</P_SubElement6>
<M_AddElement1>0</M_AddElement1>
<M_AddElement2>0</M_AddElement2>
<M_AddElement3>0</M_AddElement3>
<M_AddElement4>0</M_AddElement4>
<M_AddElement5>0</M_AddElement5>
<M_AddElement6>0</M_AddElement6>
</Details>
<CharacterData>
<Character id="cUid0">
<CharacterUID>0</CharacterUID>
<CharacterName>ソードスパイダー</CharacterName>
<CharacterType>2</CharacterType>
<InternalID>1</InternalID>
<PopSpeed>30</PopSpeed>
<PopPoint_X>113.38</PopPoint_X>
<PopPoint_Y>65.00</PopPoint_Y>
</Character>
<Character id="cUid1">
<CharacterUID>1</CharacterUID>
<CharacterName>ソードスパイダー</CharacterName>
<CharacterType>2</CharacterType>
<InternalID>1</InternalID>
<PopSpeed>30</PopSpeed>
<PopPoint_X>119.69</PopPoint_X>
<PopPoint_Y>59.50</PopPoint_Y>
</Character>
<Character id="cUid2">
<CharacterUID>2</CharacterUID>
<CharacterName>ソードスパイダー</CharacterName>
<CharacterType>2</CharacterType>
<InternalID>1</InternalID>
<PopSpeed>30</PopSpeed>
<PopPoint_X>134.63</PopPoint_X>
<PopPoint_Y>71.56</PopPoint_Y>
</Character>
<Character id="cUid3">
<CharacterUID>3</CharacterUID>
<CharacterName>ソードスパイダー</CharacterName>
<CharacterType>2</CharacterType>
<InternalID>1</InternalID>
<PopSpeed>30</PopSpeed>
<PopPoint_X>144.19</PopPoint_X>
<PopPoint_Y>66.75</PopPoint_Y>
</Character>
<Character id="cUid4">
<CharacterUID>4</CharacterUID>
<CharacterName>ソードスパイダー</CharacterName>
<CharacterType>2</CharacterType>
<InternalID>1</InternalID>
<PopSpeed>30</PopSpeed>
<PopPoint_X>133.00</PopPoint_X>
<PopPoint_Y>64.38</PopPoint_Y>
</Character>
<Character id="cUid5">
<CharacterUID>5</CharacterUID>
<CharacterName>ブラックメイジ</CharacterName>
<CharacterType>2</CharacterType>
<InternalID>0</InternalID>
<PopSpeed>35</PopSpeed>
<PopPoint_X>126.63</PopPoint_X>
<PopPoint_Y>62.38</PopPoint_Y>
</Character>
<Character id="cUid6">
<CharacterUID>6</CharacterUID>
<CharacterName>ブラックメイジ</CharacterName>
<CharacterType>2</CharacterType>
<InternalID>3</InternalID>
<PopSpeed>35</PopSpeed>
<PopPoint_X>163.31</PopPoint_X>
<PopPoint_Y>35.19</PopPoint_Y>
</Character>
<Character id="cUid7">
<CharacterUID>7</CharacterUID>
<CharacterName>ソードスパイダー</CharacterName>
<CharacterType>2</CharacterType>
<InternalID>1</InternalID>
<PopSpeed>30</PopSpeed>
<PopPoint_X>154.66</PopPoint_X>
<PopPoint_Y>41.06</PopPoint_Y>
</Character>
<Character id="cUid8">
<CharacterUID>8</CharacterUID>
<CharacterName>ソードスパイダー</CharacterName>
<CharacterType>2</CharacterType>
<InternalID>1</InternalID>
<PopSpeed>30</PopSpeed>
<PopPoint_X>169.25</PopPoint_X>
<PopPoint_Y>39.00</PopPoint_Y>
</Character>
<Character id="cUid9">
<CharacterUID>9</CharacterUID>
<CharacterName>ソードスパイダー</CharacterName>
<CharacterType>2</CharacterType>
<InternalID>1</InternalID>
<PopSpeed>30</PopSpeed>
<PopPoint_X>172.44</PopPoint_X>
<PopPoint_Y>28.78</PopPoint_Y>
</Character>
<Character id="cUid10">
<CharacterUID>10</CharacterUID>
<CharacterName>ソードスパイダー</CharacterName>
<CharacterType>2</CharacterType>
<InternalID>1</InternalID>
<PopSpeed>30</PopSpeed>
<PopPoint_X>157.03</PopPoint_X>
<PopPoint_Y>31.75</PopPoint_Y>
</Character>
<Character id="cUid11">
<CharacterUID>11</CharacterUID>
<CharacterName>ソードスパイダー</CharacterName>
<CharacterType>2</CharacterType>
<InternalID>1</InternalID>
<PopSpeed>30</PopSpeed>
<PopPoint_X>180.53</PopPoint_X>
<PopPoint_Y>16.44</PopPoint_Y>
</Character>
<Character id="cUid12">
<CharacterUID>12</CharacterUID>
<CharacterName>ソードスパイダー</CharacterName>
<CharacterType>2</CharacterType>
<InternalID>1</InternalID>
<PopSpeed>30</PopSpeed>
<PopPoint_X>200.53</PopPoint_X>
<PopPoint_Y>16.88</PopPoint_Y>
</Character>
<Character id="cUid13">
<CharacterUID>13</CharacterUID>
<CharacterName>ブラックメイジ</CharacterName>
<CharacterType>2</CharacterType>
<InternalID>3</InternalID>
<PopSpeed>35</PopSpeed>
<PopPoint_X>186.47</PopPoint_X>
<PopPoint_Y>16.75</PopPoint_Y>
</Character>
<Character id="cUid14">
<CharacterUID>14</CharacterUID>
<CharacterName>ブラックメイジ</CharacterName>
<CharacterType>2</CharacterType>
<InternalID>3</InternalID>
<PopSpeed>35</PopSpeed>
<PopPoint_X>194.97</PopPoint_X>
<PopPoint_Y>14.47</PopPoint_Y>
</Character>
<Character id="cUid15">
<CharacterUID>15</CharacterUID>
<CharacterName>ブラックメイジ</CharacterName>
<CharacterType>2</CharacterType>
<InternalID>0</InternalID>
<PopSpeed>35</PopSpeed>
<PopPoint_X>207.69</PopPoint_X>
<PopPoint_Y>31.47</PopPoint_Y>
</Character>
<Character id="cUid16">
<CharacterUID>16</CharacterUID>
<CharacterName>ブラックメイジ</CharacterName>
<CharacterType>2</CharacterType>
<InternalID>3</InternalID>
<PopSpeed>35</PopSpeed>
<PopPoint_X>203.84</PopPoint_X>
<PopPoint_Y>56.34</PopPoint_Y>
</Character>
<Character id="cUid17">
<CharacterUID>17</CharacterUID>
<CharacterName>ソードスパイダー</CharacterName>
<CharacterType>2</CharacterType>
<InternalID>1</InternalID>
<PopSpeed>30</PopSpeed>
<PopPoint_X>208.97</PopPoint_X>
<PopPoint_Y>57.19</PopPoint_Y>
</Character>
<Character id="cUid18">
<CharacterUID>18</CharacterUID>
<CharacterName>ソードスパイダー</CharacterName>
<CharacterType>2</CharacterType>
<InternalID>1</InternalID>
<PopSpeed>30</PopSpeed>
<PopPoint_X>201.44</PopPoint_X>
<PopPoint_Y>44.38</PopPoint_Y>
</Character>
<Character id="cUid19">
<CharacterUID>19</CharacterUID>
<CharacterName>ソードスパイダー</CharacterName>
<CharacterType>2</CharacterType>
<InternalID>1</InternalID>
<PopSpeed>30</PopSpeed>
<PopPoint_X>201.44</PopPoint_X>
<PopPoint_Y>34.50</PopPoint_Y>
</Character>
<Character id="cUid20">
<CharacterUID>20</CharacterUID>
<CharacterName>ソードスパイダー</CharacterName>
<CharacterType>2</CharacterType>
<InternalID>1</InternalID>
<PopSpeed>30</PopSpeed>
<PopPoint_X>199.75</PopPoint_X>
<PopPoint_Y>77.81</PopPoint_Y>
</Character>
<Character id="cUid21">
<CharacterUID>21</CharacterUID>
<CharacterName>ソードスパイダー</CharacterName>
<CharacterType>2</CharacterType>
<InternalID>1</InternalID>
<PopSpeed>30</PopSpeed>
<PopPoint_X>212.00</PopPoint_X>
<PopPoint_Y>83.66</PopPoint_Y>
</Character>
<Character id="cUid22">
<CharacterUID>22</CharacterUID>
<CharacterName>ソードスパイダー</CharacterName>
<CharacterType>2</CharacterType>
<InternalID>1</InternalID>
<PopSpeed>30</PopSpeed>
<PopPoint_X>220.06</PopPoint_X>
<PopPoint_Y>77.22</PopPoint_Y>
</Character>
<Character id="cUid23">
<CharacterUID>23</CharacterUID>
<CharacterName>ブラックメイジ</CharacterName>
<CharacterType>2</CharacterType>
<InternalID>0</InternalID>
<PopSpeed>35</PopSpeed>
<PopPoint_X>212.16</PopPoint_X>
<PopPoint_Y>80.94</PopPoint_Y>
</Character>
<Character id="cUid24">
<CharacterUID>24</CharacterUID>
<CharacterName>ブラックメイジ</CharacterName>
<CharacterType>2</CharacterType>
<InternalID>0</InternalID>
<PopSpeed>25</PopSpeed>
<PopPoint_X>54.34</PopPoint_X>
<PopPoint_Y>47.09</PopPoint_Y>
</Character>
<Character id="cUid25">
<CharacterUID>25</CharacterUID>
<CharacterName>ブラックメイジ</CharacterName>
<CharacterType>2</CharacterType>
<InternalID>0</InternalID>
<PopSpeed>25</PopSpeed>
<PopPoint_X>62.63</PopPoint_X>
<PopPoint_Y>57.81</PopPoint_Y>
</Character>
<Character id="cUid26">
<CharacterUID>26</CharacterUID>
<CharacterName>ソードスパイダー</CharacterName>
<CharacterType>2</CharacterType>
<InternalID>1</InternalID>
<PopSpeed>16</PopSpeed>
<PopPoint_X>45.72</PopPoint_X>
<PopPoint_Y>46.25</PopPoint_Y>
</Character>
<Character id="cUid27">
<CharacterUID>27</CharacterUID>
<CharacterName>ソードスパイダー</CharacterName>
<CharacterType>2</CharacterType>
<InternalID>1</InternalID>
<PopSpeed>15</PopSpeed>
<PopPoint_X>46.44</PopPoint_X>
<PopPoint_Y>58.81</PopPoint_Y>
</Character>
<Character id="cUid28">
<CharacterUID>28</CharacterUID>
<CharacterName>ソードスパイダー</CharacterName>
<CharacterType>2</CharacterType>
<InternalID>1</InternalID>
<PopSpeed>15</PopSpeed>
<PopPoint_X>69.44</PopPoint_X>
<PopPoint_Y>58.75</PopPoint_Y>
</Character>
<Character id="cUid29">
<CharacterUID>29</CharacterUID>
<CharacterName>ソードスパイダー</CharacterName>
<CharacterType>2</CharacterType>
<InternalID>1</InternalID>
<PopSpeed>15</PopSpeed>
<PopPoint_X>68.88</PopPoint_X>
<PopPoint_Y>46.44</PopPoint_Y>
</Character>
<Character id="cUid30">
<CharacterUID>30</CharacterUID>
<CharacterName>ソードスパイダー</CharacterName>
<CharacterType>2</CharacterType>
<InternalID>1</InternalID>
<PopSpeed>16</PopSpeed>
<PopPoint_X>53.63</PopPoint_X>
<PopPoint_Y>57.19</PopPoint_Y>
</Character>
<Character id="cUid31">
<CharacterUID>31</CharacterUID>
<CharacterName>ソードスパイダー</CharacterName>
<CharacterType>2</CharacterType>
<InternalID>1</InternalID>
<PopSpeed>30</PopSpeed>
<PopPoint_X>55.28</PopPoint_X>
<PopPoint_Y>31.09</PopPoint_Y>
</Character>
<Character id="cUid32">
<CharacterUID>32</CharacterUID>
<CharacterName>ソードスパイダー</CharacterName>
<CharacterType>2</CharacterType>
<InternalID>1</InternalID>
<PopSpeed>30</PopSpeed>
<PopPoint_X>74.47</PopPoint_X>
<PopPoint_Y>22.50</PopPoint_Y>
</Character>
<Character id="cUid33">
<CharacterUID>33</CharacterUID>
<CharacterName>ソードスパイダー</CharacterName>
<CharacterType>2</CharacterType>
<InternalID>1</InternalID>
<PopSpeed>30</PopSpeed>
<PopPoint_X>44.63</PopPoint_X>
<PopPoint_Y>27.84</PopPoint_Y>
</Character>
<Character id="cUid34">
<CharacterUID>34</CharacterUID>
<CharacterName>ブラックメイジ</CharacterName>
<CharacterType>2</CharacterType>
<InternalID>0</InternalID>
<PopSpeed>35</PopSpeed>
<PopPoint_X>53.78</PopPoint_X>
<PopPoint_Y>21.94</PopPoint_Y>
</Character>
<Character id="cUid35">
<CharacterUID>35</CharacterUID>
<CharacterName>ブラックメイジ</CharacterName>
<CharacterType>2</CharacterType>
<InternalID>3</InternalID>
<PopSpeed>35</PopSpeed>
<PopPoint_X>69.66</PopPoint_X>
<PopPoint_Y>32.25</PopPoint_Y>
</Character>
<Character id="cUid36">
<CharacterUID>36</CharacterUID>
<CharacterName>ソードスパイダー</CharacterName>
<CharacterType>2</CharacterType>
<InternalID>1</InternalID>
<PopSpeed>30</PopSpeed>
<PopPoint_X>66.63</PopPoint_X>
<PopPoint_Y>25.13</PopPoint_Y>
</Character>
<Character id="cUid37">
<CharacterUID>37</CharacterUID>
<CharacterName>ソードスパイダー</CharacterName>
<CharacterType>2</CharacterType>
<InternalID>1</InternalID>
<PopSpeed>30</PopSpeed>
<PopPoint_X>16.31</PopPoint_X>
<PopPoint_Y>14.44</PopPoint_Y>
</Character>
<Character id="cUid38">
<CharacterUID>38</CharacterUID>
<CharacterName>ソードスパイダー</CharacterName>
<CharacterType>2</CharacterType>
<InternalID>1</InternalID>
<PopSpeed>30</PopSpeed>
<PopPoint_X>23.56</PopPoint_X>
<PopPoint_Y>26.19</PopPoint_Y>
</Character>
<Character id="cUid39">
<CharacterUID>39</CharacterUID>
<CharacterName>ブラックメイジ</CharacterName>
<CharacterType>2</CharacterType>
<InternalID>3</InternalID>
<PopSpeed>35</PopSpeed>
<PopPoint_X>19.31</PopPoint_X>
<PopPoint_Y>22.00</PopPoint_Y>
</Character>
<Character id="cUid40">
<CharacterUID>40</CharacterUID>
<CharacterName>ブラックメイジ</CharacterName>
<CharacterType>2</CharacterType>
<InternalID>0</InternalID>
<PopSpeed>35</PopSpeed>
<PopPoint_X>27.63</PopPoint_X>
<PopPoint_Y>14.31</PopPoint_Y>
</Character>
<Character id="cUid41">
<CharacterUID>41</CharacterUID>
<CharacterName>ブラックメイジ</CharacterName>
<CharacterType>2</CharacterType>
<InternalID>0</InternalID>
<PopSpeed>35</PopSpeed>
<PopPoint_X>90.88</PopPoint_X>
<PopPoint_Y>36.97</PopPoint_Y>
</Character>
<Character id="cUid42">
<CharacterUID>42</CharacterUID>
<CharacterName>ブラックメイジ</CharacterName>
<CharacterType>2</CharacterType>
<InternalID>3</InternalID>
<PopSpeed>35</PopSpeed>
<PopPoint_X>93.47</PopPoint_X>
<PopPoint_Y>52.50</PopPoint_Y>
</Character>
<Character id="cUid43">
<CharacterUID>43</CharacterUID>
<CharacterName>ソードスパイダー</CharacterName>
<CharacterType>2</CharacterType>
<InternalID>1</InternalID>
<PopSpeed>30</PopSpeed>
<PopPoint_X>94.88</PopPoint_X>
<PopPoint_Y>39.41</PopPoint_Y>
</Character>
<Character id="cUid44">
<CharacterUID>44</CharacterUID>
<CharacterName>ソードスパイダー</CharacterName>
<CharacterType>2</CharacterType>
<InternalID>1</InternalID>
<PopSpeed>30</PopSpeed>
<PopPoint_X>90.97</PopPoint_X>
<PopPoint_Y>49.38</PopPoint_Y>
</Character>
<Character id="cUid45">
<CharacterUID>45</CharacterUID>
<CharacterName>ソードスパイダー</CharacterName>
<CharacterType>2</CharacterType>
<InternalID>1</InternalID>
<PopSpeed>30</PopSpeed>
<PopPoint_X>100.94</PopPoint_X>
<PopPoint_Y>44.75</PopPoint_Y>
</Character>
<Character id="cUid46">
<CharacterUID>46</CharacterUID>
<CharacterName>ソードスパイダー</CharacterName>
<CharacterType>2</CharacterType>
<InternalID>1</InternalID>
<PopSpeed>30</PopSpeed>
<PopPoint_X>15.69</PopPoint_X>
<PopPoint_Y>59.25</PopPoint_Y>
</Character>
<Character id="cUid47">
<CharacterUID>47</CharacterUID>
<CharacterName>ソードスパイダー</CharacterName>
<CharacterType>2</CharacterType>
<InternalID>1</InternalID>
<PopSpeed>30</PopSpeed>
<PopPoint_X>19.59</PopPoint_X>
<PopPoint_Y>74.00</PopPoint_Y>
</Character>
<Character id="cUid48">
<CharacterUID>48</CharacterUID>
<CharacterName>ソードスパイダー</CharacterName>
<CharacterType>2</CharacterType>
<InternalID>1</InternalID>
<PopSpeed>30</PopSpeed>
<PopPoint_X>33.69</PopPoint_X>
<PopPoint_Y>71.28</PopPoint_Y>
</Character>
<Character id="cUid49">
<CharacterUID>49</CharacterUID>
<CharacterName>ブラックメイジ</CharacterName>
<CharacterType>2</CharacterType>
<InternalID>0</InternalID>
<PopSpeed>35</PopSpeed>
<PopPoint_X>26.38</PopPoint_X>
<PopPoint_Y>72.06</PopPoint_Y>
</Character>
<Character id="cUid50">
<CharacterUID>50</CharacterUID>
<CharacterName>ブラックメイジ</CharacterName>
<CharacterType>2</CharacterType>
<InternalID>3</InternalID>
<PopSpeed>35</PopSpeed>
<PopPoint_X>14.22</PopPoint_X>
<PopPoint_Y>66.63</PopPoint_Y>
</Character>
<Character id="cUid51">
<CharacterUID>51</CharacterUID>
<CharacterName>ブラックメイジ</CharacterName>
<CharacterType>2</CharacterType>
<InternalID>0</InternalID>
<PopSpeed>35</PopSpeed>
<PopPoint_X>74.13</PopPoint_X>
<PopPoint_Y>72.47</PopPoint_Y>
</Character>
<Character id="cUid52">
<CharacterUID>52</CharacterUID>
<CharacterName>ソードスパイダー</CharacterName>
<CharacterType>2</CharacterType>
<InternalID>1</InternalID>
<PopSpeed>30</PopSpeed>
<PopPoint_X>84.66</PopPoint_X>
<PopPoint_Y>72.31</PopPoint_Y>
</Character>
<Character id="cUid53">
<CharacterUID>53</CharacterUID>
<CharacterName>ソードスパイダー</CharacterName>
<CharacterType>2</CharacterType>
<InternalID>1</InternalID>
<PopSpeed>30</PopSpeed>
<PopPoint_X>78.78</PopPoint_X>
<PopPoint_Y>79.25</PopPoint_Y>
</Character>
<Character id="cUid54">
<CharacterUID>54</CharacterUID>
<CharacterName>ソードスパイダー</CharacterName>
<CharacterType>2</CharacterType>
<InternalID>1</InternalID>
<PopSpeed>30</PopSpeed>
<PopPoint_X>111.34</PopPoint_X>
<PopPoint_Y>86.84</PopPoint_Y>
</Character>
<Character id="cUid55">
<CharacterUID>55</CharacterUID>
<CharacterName>ブラックメイジ</CharacterName>
<CharacterType>2</CharacterType>
<InternalID>3</InternalID>
<PopSpeed>35</PopSpeed>
<PopPoint_X>92.81</PopPoint_X>
<PopPoint_Y>88.94</PopPoint_Y>
</Character>
<Character id="cUid56">
<CharacterUID>56</CharacterUID>
<CharacterName>ソードスパイダー</CharacterName>
<CharacterType>2</CharacterType>
<InternalID>1</InternalID>
<PopSpeed>30</PopSpeed>
<PopPoint_X>104.13</PopPoint_X>
<PopPoint_Y>89.28</PopPoint_Y>
</Character>
<Character id="cUid57">
<CharacterUID>57</CharacterUID>
<CharacterName>ウィーブウィドウ</CharacterName>
<CharacterType>2</CharacterType>
<InternalID>2</InternalID>
<PopSpeed>330</PopSpeed>
<PopPoint_X>57.97</PopPoint_X>
<PopPoint_Y>52.06</PopPoint_Y>
</Character>
<Character id="cUid58">
<CharacterUID>58</CharacterUID>
<CharacterName>ソードスパイダー</CharacterName>
<CharacterType>2</CharacterType>
<InternalID>1</InternalID>
<PopSpeed>15</PopSpeed>
<PopPoint_X>62.16</PopPoint_X>
<PopPoint_Y>47.06</PopPoint_Y>
</Character>
</CharacterData>
<AreaData>
<Area id="aUid0">
<AreaUID>0</AreaUID>
<AreaName>_필드 전체</AreaName>
<AreaType>0</AreaType>
<AccessMap></AccessMap>
<AccessMapName></AccessMapName>
<AreaPos_X>0.00</AreaPos_X>
<AreaPos_X2>0.00</AreaPos_X2>
<AreaPos_Y>0.00</AreaPos_Y>
<AreaPos_Y2>0.00</AreaPos_Y2>
<AreaExpansion>
</AreaExpansion>
</Area>
<Area id="aUid1">
<AreaUID>1</AreaUID>
<AreaName>_화면</AreaName>
<AreaType>0</AreaType>
<AccessMap></AccessMap>
<AccessMapName></AccessMapName>
<AreaPos_X>0.00</AreaPos_X>
<AreaPos_X2>0.00</AreaPos_X2>
<AreaPos_Y>0.00</AreaPos_Y>
<AreaPos_Y2>0.00</AreaPos_Y2>
<AreaExpansion>
</AreaExpansion>
</Area>
<Area id="aUid2">
<AreaUID>2</AreaUID>
<AreaName>지하 5층으로</AreaName>
<AreaType>3</AreaType>
<AccessMap>[041]M12_M01_B05.rmd</AccessMap>
<AccessMapName>廃坑　Ｂ５</AccessMapName>
<AreaPos_X>132.63</AreaPos_X>
<AreaPos_X2>138.50</AreaPos_X2>
<AreaPos_Y>1.56</AreaPos_Y>
<AreaPos_Y2>4.41</AreaPos_Y2>
<AreaExpansion>
</AreaExpansion>
</Area>
<Area id="aUid3">
<AreaUID>3</AreaUID>
<AreaName>지하 7층으로</AreaName>
<AreaType>3</AreaType>
<AccessMap>[043]M12_M01_B07.rmd</AccessMap>
<AccessMapName>廃坑　Ｂ７</AccessMapName>
<AreaPos_X>163.81</AreaPos_X>
<AreaPos_X2>168.84</AreaPos_X2>
<AreaPos_Y>95.69</AreaPos_Y>
<AreaPos_Y2>98.63</AreaPos_Y2>
<AreaExpansion>
</AreaExpansion>
</Area>
<Area id="aUid4">
<AreaUID>4</AreaUID>
<AreaName>Area 3</AreaName>
<AreaType>4</AreaType>
<AccessMap></AccessMap>
<AccessMapName></AccessMapName>
<AreaPos_X>195.00</AreaPos_X>
<AreaPos_X2>224.66</AreaPos_X2>
<AreaPos_Y>72.91</AreaPos_Y>
<AreaPos_Y2>85.88</AreaPos_Y2>
<AreaExpansion>
</AreaExpansion>
</Area>
<Area id="aUid5">
<AreaUID>5</AreaUID>
<AreaName>Area 4</AreaName>
<AreaType>4</AreaType>
<AccessMap></AccessMap>
<AccessMapName></AccessMapName>
<AreaPos_X>107.88</AreaPos_X>
<AreaPos_X2>148.50</AreaPos_X2>
<AreaPos_Y>58.00</AreaPos_Y>
<AreaPos_Y2>73.25</AreaPos_Y2>
<AreaExpansion>
</AreaExpansion>
</Area>
<Area id="aUid6">
<AreaUID>6</AreaUID>
<AreaName>Area 5</AreaName>
<AreaType>4</AreaType>
<AccessMap></AccessMap>
<AccessMapName></AccessMapName>
<AreaPos_X>174.06</AreaPos_X>
<AreaPos_X2>205.88</AreaPos_X2>
<AreaPos_Y>6.63</AreaPos_Y>
<AreaPos_Y2>18.25</AreaPos_Y2>
<AreaExpansion>
</AreaExpansion>
</Area>
<Area id="aUid7">
<AreaUID>7</AreaUID>
<AreaName>Area 6</AreaName>
<AreaType>4</AreaType>
<AccessMap></AccessMap>
<AccessMapName></AccessMapName>
<AreaPos_X>150.00</AreaPos_X>
<AreaPos_X2>179.50</AreaPos_X2>
<AreaPos_Y>25.25</AreaPos_Y>
<AreaPos_Y2>44.47</AreaPos_Y2>
<AreaExpansion>
</AreaExpansion>
</Area>
<Area id="aUid8">
<AreaUID>8</AreaUID>
<AreaName>Area 7</AreaName>
<AreaType>4</AreaType>
<AccessMap></AccessMap>
<AccessMapName></AccessMapName>
<AreaPos_X>90.03</AreaPos_X>
<AreaPos_X2>115.94</AreaPos_X2>
<AreaPos_Y>83.31</AreaPos_Y>
<AreaPos_Y2>94.00</AreaPos_Y2>
<AreaExpansion>
</AreaExpansion>
</Area>
<Area id="aUid9">
<AreaUID>9</AreaUID>
<AreaName>Area 8</AreaName>
<AreaType>4</AreaType>
<AccessMap></AccessMap>
<AccessMapName></AccessMapName>
<AreaPos_X>60.03</AreaPos_X>
<AreaPos_X2>71.97</AreaPos_X2>
<AreaPos_Y>44.97</AreaPos_Y>
<AreaPos_Y2>59.94</AreaPos_Y2>
<AreaExpansion>
</AreaExpansion>
</Area>
<Area id="aUid10">
<AreaUID>10</AreaUID>
<AreaName>Area 9</AreaName>
<AreaType>4</AreaType>
<AccessMap></AccessMap>
<AccessMapName></AccessMapName>
<AreaPos_X>61.97</AreaPos_X>
<AreaPos_X2>76.25</AreaPos_X2>
<AreaPos_Y>18.56</AreaPos_Y>
<AreaPos_Y2>37.50</AreaPos_Y2>
<AreaExpansion>
</AreaExpansion>
</Area>
<Area id="aUid11">
<AreaUID>11</AreaUID>
<AreaName>Area 10</AreaName>
<AreaType>4</AreaType>
<AccessMap></AccessMap>
<AccessMapName></AccessMapName>
<AreaPos_X>43.91</AreaPos_X>
<AreaPos_X2>56.00</AreaPos_X2>
<AreaPos_Y>44.91</AreaPos_Y>
<AreaPos_Y2>60.13</AreaPos_Y2>
<AreaExpansion>
</AreaExpansion>
</Area>
<Area id="aUid12">
<AreaUID>12</AreaUID>
<AreaName>Area 11</AreaName>
<AreaType>4</AreaType>
<AccessMap></AccessMap>
<AccessMapName></AccessMapName>
<AreaPos_X>23.44</AreaPos_X>
<AreaPos_X2>37.25</AreaPos_X2>
<AreaPos_Y>63.84</AreaPos_Y>
<AreaPos_Y2>79.38</AreaPos_Y2>
<AreaExpansion>
</AreaExpansion>
</Area>
<Area id="aUid13">
<AreaUID>13</AreaUID>
<AreaName>Area 12</AreaName>
<AreaType>4</AreaType>
<AccessMap></AccessMap>
<AccessMapName></AccessMapName>
<AreaPos_X>43.19</AreaPos_X>
<AreaPos_X2>57.50</AreaPos_X2>
<AreaPos_Y>17.41</AreaPos_Y>
<AreaPos_Y2>36.38</AreaPos_Y2>
<AreaExpansion>
</AreaExpansion>
</Area>
<Area id="aUid14">
<AreaUID>14</AreaUID>
<AreaName>Area 13</AreaName>
<AreaType>4</AreaType>
<AccessMap></AccessMap>
<AccessMapName></AccessMapName>
<AreaPos_X>12.94</AreaPos_X>
<AreaPos_X2>32.63</AreaPos_X2>
<AreaPos_Y>10.16</AreaPos_Y>
<AreaPos_Y2>29.75</AreaPos_Y2>
<AreaExpansion>
</AreaExpansion>
</Area>
<Area id="aUid15">
<AreaUID>15</AreaUID>
<AreaName>Area 14</AreaName>
<AreaType>4</AreaType>
<AccessMap></AccessMap>
<AccessMapName></AccessMapName>
<AreaPos_X>6.09</AreaPos_X>
<AreaPos_X2>22.75</AreaPos_X2>
<AreaPos_Y>56.09</AreaPos_Y>
<AreaPos_Y2>80.81</AreaPos_Y2>
<AreaExpansion>
</AreaExpansion>
</Area>
<Area id="aUid16">
<AreaUID>16</AreaUID>
<AreaName>Area 15</AreaName>
<AreaType>4</AreaType>
<AccessMap></AccessMap>
<AccessMapName></AccessMapName>
<AreaPos_X>41.97</AreaPos_X>
<AreaPos_X2>73.91</AreaPos_X2>
<AreaPos_Y>44.50</AreaPos_Y>
<AreaPos_Y2>60.66</AreaPos_Y2>
<AreaExpansion>
</AreaExpansion>
</Area>
<Area id="aUid17">
<AreaUID>17</AreaUID>
<AreaName>Area 16</AreaName>
<AreaType>4</AreaType>
<AccessMap></AccessMap>
<AccessMapName></AccessMapName>
<AreaPos_X>67.09</AreaPos_X>
<AreaPos_X2>89.88</AreaPos_X2>
<AreaPos_Y>69.09</AreaPos_Y>
<AreaPos_Y2>81.53</AreaPos_Y2>
<AreaExpansion>
</AreaExpansion>
</Area>
<Area id="aUid18">
<AreaUID>18</AreaUID>
<AreaName>Area 17</AreaName>
<AreaType>4</AreaType>
<AccessMap></AccessMap>
<AccessMapName></AccessMapName>
<AreaPos_X>195.16</AreaPos_X>
<AreaPos_X2>211.63</AreaPos_X2>
<AreaPos_Y>28.75</AreaPos_Y>
<AreaPos_Y2>59.19</AreaPos_Y2>
<AreaExpansion>
</AreaExpansion>
</Area>
<Area id="aUid19">
<AreaUID>19</AreaUID>
<AreaName>Area 18</AreaName>
<AreaType>4</AreaType>
<AccessMap></AccessMap>
<AccessMapName></AccessMapName>
<AreaPos_X>87.50</AreaPos_X>
<AreaPos_X2>102.75</AreaPos_X2>
<AreaPos_Y>33.25</AreaPos_Y>
<AreaPos_Y2>55.88</AreaPos_Y2>
<AreaExpansion>
</AreaExpansion>
</Area>
<Area id="aUid20">
<AreaUID>20</AreaUID>
<AreaName>보물상자00</AreaName>
<AreaType>13</AreaType>
<AccessMap></AccessMap>
<AccessMapName></AccessMapName>
<AreaPos_X>56.06</AreaPos_X>
<AreaPos_X2>58.00</AreaPos_X2>
<AreaPos_Y>15.00</AreaPos_Y>
<AreaPos_Y2>16.09</AreaPos_Y2>
<AreaExpansion>
</AreaExpansion>
</Area>
<Area id="aUid21">
<AreaUID>21</AreaUID>
<AreaName>보물상자01</AreaName>
<AreaType>13</AreaType>
<AccessMap></AccessMap>
<AccessMapName></AccessMapName>
<AreaPos_X>20.03</AreaPos_X>
<AreaPos_X2>21.94</AreaPos_X2>
<AreaPos_Y>61.13</AreaPos_Y>
<AreaPos_Y2>62.25</AreaPos_Y2>
<AreaExpansion>
</AreaExpansion>
</Area>
<Area id="aUid22">
<AreaUID>22</AreaUID>
<AreaName>보물상자02</AreaName>
<AreaType>13</AreaType>
<AccessMap></AccessMap>
<AccessMapName></AccessMapName>
<AreaPos_X>115.81</AreaPos_X>
<AreaPos_X2>117.69</AreaPos_X2>
<AreaPos_Y>88.41</AreaPos_Y>
<AreaPos_Y2>89.47</AreaPos_Y2>
<AreaExpansion>
</AreaExpansion>
</Area>
<Area id="aUid23">
<AreaUID>23</AreaUID>
<AreaName>보물상자03</AreaName>
<AreaType>13</AreaType>
<AccessMap></AccessMap>
<AccessMapName></AccessMapName>
<AreaPos_X>217.44</AreaPos_X>
<AreaPos_X2>219.31</AreaPos_X2>
<AreaPos_Y>17.41</AreaPos_Y>
<AreaPos_Y2>18.44</AreaPos_Y2>
<AreaExpansion>
</AreaExpansion>
</Area>
<Area id="aUid24">
<AreaUID>24</AreaUID>
<AreaName>보물상자04</AreaName>
<AreaType>13</AreaType>
<AccessMap></AccessMap>
<AccessMapName></AccessMapName>
<AreaPos_X>220.06</AreaPos_X>
<AreaPos_X2>221.88</AreaPos_X2>
<AreaPos_Y>54.81</AreaPos_Y>
<AreaPos_Y2>55.81</AreaPos_Y2>
<AreaExpansion>
</AreaExpansion>
</Area>
<Area id="aUid25">
<AreaUID>25</AreaUID>
<AreaName>보물상자05</AreaName>
<AreaType>13</AreaType>
<AccessMap></AccessMap>
<AccessMapName></AccessMapName>
<AreaPos_X>148.09</AreaPos_X>
<AreaPos_X2>149.91</AreaPos_X2>
<AreaPos_Y>48.00</AreaPos_Y>
<AreaPos_Y2>49.00</AreaPos_Y2>
<AreaExpansion>
</AreaExpansion>
</Area>
<Area id="aUid26">
<AreaUID>26</AreaUID>
<AreaName>금광</AreaName>
<AreaType>2</AreaType>
<AccessMap></AccessMap>
<AccessMapName></AccessMapName>
<AreaPos_X>79.97</AreaPos_X>
<AreaPos_X2>92.16</AreaPos_X2>
<AreaPos_Y>8.81</AreaPos_Y>
<AreaPos_Y2>18.16</AreaPos_Y2>
<AreaExpansion>
<Door_Endurance>10000</Door_Endurance>
<DetectSecretDoor_Lv>0</DetectSecretDoor_Lv>
<UnlockDoor_Lv>0</UnlockDoor_Lv>
<RecoveryTime>30</RecoveryTime>
<isMortalObject>1</isMortalObject>
<DisarmTrap_Lv>0</DisarmTrap_Lv>
<DetectTrap_Lv>0</DetectTrap_Lv>
<TrapID1>65535</TrapID1>
<TrapID2>65535</TrapID2>
<isSecretDungeonEntrance>1</isSecretDungeonEntrance>
</AreaExpansion>
</Area>
</AreaData>
</MapData>
