<?xml version="1.0" encoding="utf-8"?>
<MapData>
<Details>
<FileName>[197]T08_S01_B02.rmd</FileName>
<FileType>Red Stone Scenario File 6.1 beta</FileType>
<MapName>アリアン遺跡　Ｂ２</MapName>
<SysWidth>85</SysWidth>
<SysHeight>85</SysHeight>
<TgaWidth>170</TgaWidth>
<TgaHeight>85</TgaHeight>
<MapType>1</MapType>
<isPremiumMap>1</isPremiumMap>
<isPvPMap>0</isPvPMap>
<MapView_Lv>0</MapView_Lv>
<isLocationStrage>1</isLocationStrage>
<P_SubElement1>0</P_SubElement1>
<P_SubElement2>0</P_SubElement2>
<P_SubElement3>0</P_SubElement3>
<P_SubElement4>0</P_SubElement4>
<P_SubElement5>0</P_SubElement5>
<P_SubElement6>0</P_SubElement6>
<M_AddElement1>0</M_AddElement1>
<M_AddElement2>0</M_AddElement2>
<M_AddElement3>0</M_AddElement3>
<M_AddElement4>0</M_AddElement4>
<M_AddElement5>0</M_AddElement5>
<M_AddElement6>0</M_AddElement6>
</Details>
<CharacterData>
<Character id="cUid0">
<CharacterUID>0</CharacterUID>
<CharacterName>クローラー</CharacterName>
<CharacterType>2</CharacterType>
<InternalID>0</InternalID>
<PopSpeed>17</PopSpeed>
<PopPoint_X>20.66</PopPoint_X>
<PopPoint_Y>32.94</PopPoint_Y>
</Character>
<Character id="cUid1">
<CharacterUID>1</CharacterUID>
<CharacterName>クローラー</CharacterName>
<CharacterType>2</CharacterType>
<InternalID>0</InternalID>
<PopSpeed>17</PopSpeed>
<PopPoint_X>23.53</PopPoint_X>
<PopPoint_Y>33.00</PopPoint_Y>
</Character>
<Character id="cUid2">
<CharacterUID>2</CharacterUID>
<CharacterName>クローラー</CharacterName>
<CharacterType>2</CharacterType>
<InternalID>0</InternalID>
<PopSpeed>17</PopSpeed>
<PopPoint_X>26.47</PopPoint_X>
<PopPoint_Y>33.00</PopPoint_Y>
</Character>
<Character id="cUid3">
<CharacterUID>3</CharacterUID>
<CharacterName>ブラウンベアー</CharacterName>
<CharacterType>2</CharacterType>
<InternalID>2</InternalID>
<PopSpeed>15</PopSpeed>
<PopPoint_X>84.19</PopPoint_X>
<PopPoint_Y>42.81</PopPoint_Y>
</Character>
<Character id="cUid4">
<CharacterUID>4</CharacterUID>
<CharacterName>茶色の子熊</CharacterName>
<CharacterType>2</CharacterType>
<InternalID>1</InternalID>
<PopSpeed>17</PopSpeed>
<PopPoint_X>37.59</PopPoint_X>
<PopPoint_Y>41.19</PopPoint_Y>
</Character>
<Character id="cUid5">
<CharacterUID>5</CharacterUID>
<CharacterName>茶色の子熊</CharacterName>
<CharacterType>2</CharacterType>
<InternalID>1</InternalID>
<PopSpeed>17</PopSpeed>
<PopPoint_X>41.00</PopPoint_X>
<PopPoint_Y>41.16</PopPoint_Y>
</Character>
<Character id="cUid6">
<CharacterUID>6</CharacterUID>
<CharacterName>リーチ</CharacterName>
<CharacterType>2</CharacterType>
<InternalID>3</InternalID>
<PopSpeed>17</PopSpeed>
<PopPoint_X>20.81</PopPoint_X>
<PopPoint_Y>44.47</PopPoint_Y>
</Character>
<Character id="cUid7">
<CharacterUID>7</CharacterUID>
<CharacterName>茶色の子熊</CharacterName>
<CharacterType>2</CharacterType>
<InternalID>1</InternalID>
<PopSpeed>17</PopSpeed>
<PopPoint_X>48.97</PopPoint_X>
<PopPoint_Y>41.59</PopPoint_Y>
</Character>
<Character id="cUid8">
<CharacterUID>8</CharacterUID>
<CharacterName>リーチ</CharacterName>
<CharacterType>2</CharacterType>
<InternalID>3</InternalID>
<PopSpeed>17</PopSpeed>
<PopPoint_X>43.34</PopPoint_X>
<PopPoint_Y>43.03</PopPoint_Y>
</Character>
<Character id="cUid9">
<CharacterUID>9</CharacterUID>
<CharacterName>クローラー</CharacterName>
<CharacterType>2</CharacterType>
<InternalID>0</InternalID>
<PopSpeed>15</PopSpeed>
<PopPoint_X>62.47</PopPoint_X>
<PopPoint_Y>67.94</PopPoint_Y>
</Character>
<Character id="cUid10">
<CharacterUID>10</CharacterUID>
<CharacterName>クローラー</CharacterName>
<CharacterType>2</CharacterType>
<InternalID>0</InternalID>
<PopSpeed>15</PopSpeed>
<PopPoint_X>66.66</PopPoint_X>
<PopPoint_Y>68.00</PopPoint_Y>
</Character>
<Character id="cUid11">
<CharacterUID>11</CharacterUID>
<CharacterName>茶色の子熊</CharacterName>
<CharacterType>2</CharacterType>
<InternalID>1</InternalID>
<PopSpeed>15</PopSpeed>
<PopPoint_X>64.06</PopPoint_X>
<PopPoint_Y>70.50</PopPoint_Y>
</Character>
<Character id="cUid12">
<CharacterUID>12</CharacterUID>
<CharacterName>リーチ</CharacterName>
<CharacterType>2</CharacterType>
<InternalID>3</InternalID>
<PopSpeed>15</PopSpeed>
<PopPoint_X>99.63</PopPoint_X>
<PopPoint_Y>68.50</PopPoint_Y>
</Character>
<Character id="cUid13">
<CharacterUID>13</CharacterUID>
<CharacterName>リーチ</CharacterName>
<CharacterType>2</CharacterType>
<InternalID>3</InternalID>
<PopSpeed>15</PopSpeed>
<PopPoint_X>97.28</PopPoint_X>
<PopPoint_Y>70.63</PopPoint_Y>
</Character>
<Character id="cUid14">
<CharacterUID>14</CharacterUID>
<CharacterName>リーチ</CharacterName>
<CharacterType>2</CharacterType>
<InternalID>3</InternalID>
<PopSpeed>15</PopSpeed>
<PopPoint_X>103.34</PopPoint_X>
<PopPoint_Y>69.84</PopPoint_Y>
</Character>
<Character id="cUid15">
<CharacterUID>15</CharacterUID>
<CharacterName>リーチ</CharacterName>
<CharacterType>2</CharacterType>
<InternalID>3</InternalID>
<PopSpeed>15</PopSpeed>
<PopPoint_X>103.09</PopPoint_X>
<PopPoint_Y>65.19</PopPoint_Y>
</Character>
<Character id="cUid16">
<CharacterUID>16</CharacterUID>
<CharacterName>茶色の子熊</CharacterName>
<CharacterType>2</CharacterType>
<InternalID>1</InternalID>
<PopSpeed>20</PopSpeed>
<PopPoint_X>76.72</PopPoint_X>
<PopPoint_Y>59.00</PopPoint_Y>
</Character>
<Character id="cUid17">
<CharacterUID>17</CharacterUID>
<CharacterName>リーチ</CharacterName>
<CharacterType>2</CharacterType>
<InternalID>3</InternalID>
<PopSpeed>15</PopSpeed>
<PopPoint_X>71.81</PopPoint_X>
<PopPoint_Y>71.94</PopPoint_Y>
</Character>
<Character id="cUid18">
<CharacterUID>18</CharacterUID>
<CharacterName>茶色の子熊</CharacterName>
<CharacterType>2</CharacterType>
<InternalID>1</InternalID>
<PopSpeed>20</PopSpeed>
<PopPoint_X>81.72</PopPoint_X>
<PopPoint_Y>60.22</PopPoint_Y>
</Character>
<Character id="cUid19">
<CharacterUID>19</CharacterUID>
<CharacterName>茶色の子熊</CharacterName>
<CharacterType>2</CharacterType>
<InternalID>1</InternalID>
<PopSpeed>20</PopSpeed>
<PopPoint_X>87.34</PopPoint_X>
<PopPoint_Y>60.22</PopPoint_Y>
</Character>
<Character id="cUid20">
<CharacterUID>20</CharacterUID>
<CharacterName>茶色の子熊</CharacterName>
<CharacterType>2</CharacterType>
<InternalID>8</InternalID>
<PopSpeed>15</PopSpeed>
<PopPoint_X>124.41</PopPoint_X>
<PopPoint_Y>53.00</PopPoint_Y>
</Character>
<Character id="cUid21">
<CharacterUID>21</CharacterUID>
<CharacterName>クローラー</CharacterName>
<CharacterType>2</CharacterType>
<InternalID>6</InternalID>
<PopSpeed>15</PopSpeed>
<PopPoint_X>146.56</PopPoint_X>
<PopPoint_Y>35.59</PopPoint_Y>
</Character>
<Character id="cUid22">
<CharacterUID>22</CharacterUID>
<CharacterName>クローラー</CharacterName>
<CharacterType>2</CharacterType>
<InternalID>6</InternalID>
<PopSpeed>15</PopSpeed>
<PopPoint_X>143.97</PopPoint_X>
<PopPoint_Y>34.28</PopPoint_Y>
</Character>
<Character id="cUid23">
<CharacterUID>23</CharacterUID>
<CharacterName>リーチ</CharacterName>
<CharacterType>2</CharacterType>
<InternalID>7</InternalID>
<PopSpeed>15</PopSpeed>
<PopPoint_X>141.25</PopPoint_X>
<PopPoint_Y>51.00</PopPoint_Y>
</Character>
<Character id="cUid24">
<CharacterUID>24</CharacterUID>
<CharacterName>リーチ</CharacterName>
<CharacterType>2</CharacterType>
<InternalID>7</InternalID>
<PopSpeed>15</PopSpeed>
<PopPoint_X>144.84</PopPoint_X>
<PopPoint_Y>50.75</PopPoint_Y>
</Character>
<Character id="cUid26">
<CharacterUID>26</CharacterUID>
<CharacterName>茶色の子熊</CharacterName>
<CharacterType>2</CharacterType>
<InternalID>8</InternalID>
<PopSpeed>15</PopSpeed>
<PopPoint_X>130.09</PopPoint_X>
<PopPoint_Y>53.19</PopPoint_Y>
</Character>
<Character id="cUid27">
<CharacterUID>27</CharacterUID>
<CharacterName>茶色の子熊</CharacterName>
<CharacterType>2</CharacterType>
<InternalID>8</InternalID>
<PopSpeed>15</PopSpeed>
<PopPoint_X>124.50</PopPoint_X>
<PopPoint_Y>32.56</PopPoint_Y>
</Character>
<Character id="cUid28">
<CharacterUID>28</CharacterUID>
<CharacterName>茶色の子熊</CharacterName>
<CharacterType>2</CharacterType>
<InternalID>8</InternalID>
<PopSpeed>15</PopSpeed>
<PopPoint_X>129.84</PopPoint_X>
<PopPoint_Y>32.28</PopPoint_Y>
</Character>
<Character id="cUid29">
<CharacterUID>29</CharacterUID>
<CharacterName>茶色の子熊</CharacterName>
<CharacterType>2</CharacterType>
<InternalID>8</InternalID>
<PopSpeed>15</PopSpeed>
<PopPoint_X>77.25</PopPoint_X>
<PopPoint_Y>45.84</PopPoint_Y>
</Character>
<Character id="cUid30">
<CharacterUID>30</CharacterUID>
<CharacterName>クローラー</CharacterName>
<CharacterType>2</CharacterType>
<InternalID>6</InternalID>
<PopSpeed>15</PopSpeed>
<PopPoint_X>114.63</PopPoint_X>
<PopPoint_Y>41.50</PopPoint_Y>
</Character>
<Character id="cUid31">
<CharacterUID>31</CharacterUID>
<CharacterName>リーチ</CharacterName>
<CharacterType>2</CharacterType>
<InternalID>7</InternalID>
<PopSpeed>15</PopSpeed>
<PopPoint_X>108.94</PopPoint_X>
<PopPoint_Y>42.28</PopPoint_Y>
</Character>
<Character id="cUid32">
<CharacterUID>32</CharacterUID>
<CharacterName>クローラー</CharacterName>
<CharacterType>2</CharacterType>
<InternalID>6</InternalID>
<PopSpeed>15</PopSpeed>
<PopPoint_X>112.38</PopPoint_X>
<PopPoint_Y>40.78</PopPoint_Y>
</Character>
<Character id="cUid33">
<CharacterUID>33</CharacterUID>
<CharacterName>茶色の子熊</CharacterName>
<CharacterType>2</CharacterType>
<InternalID>1</InternalID>
<PopSpeed>15</PopSpeed>
<PopPoint_X>88.69</PopPoint_X>
<PopPoint_Y>39.88</PopPoint_Y>
</Character>
<Character id="cUid34">
<CharacterUID>34</CharacterUID>
<CharacterName>リーチ</CharacterName>
<CharacterType>2</CharacterType>
<InternalID>3</InternalID>
<PopSpeed>15</PopSpeed>
<PopPoint_X>78.28</PopPoint_X>
<PopPoint_Y>42.09</PopPoint_Y>
</Character>
</CharacterData>
<AreaData>
<Area id="aUid0">
<AreaUID>0</AreaUID>
<AreaName>_필드 전체</AreaName>
<AreaType>0</AreaType>
<AccessMap></AccessMap>
<AccessMapName></AccessMapName>
<AreaPos_X>0.00</AreaPos_X>
<AreaPos_X2>0.00</AreaPos_X2>
<AreaPos_Y>0.00</AreaPos_Y>
<AreaPos_Y2>0.00</AreaPos_Y2>
<AreaExpansion>
</AreaExpansion>
</Area>
<Area id="aUid1">
<AreaUID>1</AreaUID>
<AreaName>_화면</AreaName>
<AreaType>0</AreaType>
<AccessMap></AccessMap>
<AccessMapName></AccessMapName>
<AreaPos_X>0.00</AreaPos_X>
<AreaPos_X2>0.00</AreaPos_X2>
<AreaPos_Y>0.00</AreaPos_Y>
<AreaPos_Y2>0.00</AreaPos_Y2>
<AreaExpansion>
</AreaExpansion>
</Area>
<Area id="aUid2">
<AreaUID>2</AreaUID>
<AreaName>지하 1층</AreaName>
<AreaType>3</AreaType>
<AccessMap>[196]T08_S01_B01.rmd</AccessMap>
<AccessMapName>アリアン遺跡　Ｂ１ </AccessMapName>
<AreaPos_X>81.34</AreaPos_X>
<AreaPos_X2>86.78</AreaPos_X2>
<AreaPos_Y>13.47</AreaPos_Y>
<AreaPos_Y2>16.69</AreaPos_Y2>
<AreaExpansion>
</AreaExpansion>
</Area>
<Area id="aUid3">
<AreaUID>3</AreaUID>
<AreaName>Area 2</AreaName>
<AreaType>4</AreaType>
<AccessMap></AccessMap>
<AccessMapName></AccessMapName>
<AreaPos_X>16.84</AreaPos_X>
<AreaPos_X2>30.84</AreaPos_X2>
<AreaPos_Y>27.31</AreaPos_Y>
<AreaPos_Y2>55.03</AreaPos_Y2>
<AreaExpansion>
</AreaExpansion>
</Area>
<Area id="aUid4">
<AreaUID>4</AreaUID>
<AreaName>Area 3</AreaName>
<AreaType>4</AreaType>
<AccessMap></AccessMap>
<AccessMapName></AccessMapName>
<AreaPos_X>120.66</AreaPos_X>
<AreaPos_X2>135.44</AreaPos_X2>
<AreaPos_Y>28.97</AreaPos_Y>
<AreaPos_Y2>35.75</AreaPos_Y2>
<AreaExpansion>
</AreaExpansion>
</Area>
<Area id="aUid5">
<AreaUID>5</AreaUID>
<AreaName>Area 4</AreaName>
<AreaType>4</AreaType>
<AccessMap></AccessMap>
<AccessMapName></AccessMapName>
<AreaPos_X>31.28</AreaPos_X>
<AreaPos_X2>62.19</AreaPos_X2>
<AreaPos_Y>36.09</AreaPos_Y>
<AreaPos_Y2>48.59</AreaPos_Y2>
<AreaExpansion>
</AreaExpansion>
</Area>
<Area id="aUid6">
<AreaUID>6</AreaUID>
<AreaName>Area 5</AreaName>
<AreaType>4</AreaType>
<AccessMap></AccessMap>
<AccessMapName></AccessMapName>
<AreaPos_X>56.91</AreaPos_X>
<AreaPos_X2>76.09</AreaPos_X2>
<AreaPos_Y>62.00</AreaPos_Y>
<AreaPos_Y2>78.06</AreaPos_Y2>
<AreaExpansion>
</AreaExpansion>
</Area>
<Area id="aUid7">
<AreaUID>7</AreaUID>
<AreaName>Area 6</AreaName>
<AreaType>4</AreaType>
<AccessMap></AccessMap>
<AccessMapName></AccessMapName>
<AreaPos_X>91.06</AreaPos_X>
<AreaPos_X2>110.25</AreaPos_X2>
<AreaPos_Y>62.03</AreaPos_Y>
<AreaPos_Y2>78.09</AreaPos_Y2>
<AreaExpansion>
</AreaExpansion>
</Area>
<Area id="aUid8">
<AreaUID>8</AreaUID>
<AreaName>Area 7</AreaName>
<AreaType>4</AreaType>
<AccessMap></AccessMap>
<AccessMapName></AccessMapName>
<AreaPos_X>74.09</AreaPos_X>
<AreaPos_X2>94.25</AreaPos_X2>
<AreaPos_Y>54.84</AreaPos_Y>
<AreaPos_Y2>66.28</AreaPos_Y2>
<AreaExpansion>
</AreaExpansion>
</Area>
<Area id="aUid9">
<AreaUID>9</AreaUID>
<AreaName>Area 8</AreaName>
<AreaType>4</AreaType>
<AccessMap></AccessMap>
<AccessMapName></AccessMapName>
<AreaPos_X>138.53</AreaPos_X>
<AreaPos_X2>155.59</AreaPos_X2>
<AreaPos_Y>30.09</AreaPos_Y>
<AreaPos_Y2>57.25</AreaPos_Y2>
<AreaExpansion>
</AreaExpansion>
</Area>
<Area id="aUid10">
<AreaUID>10</AreaUID>
<AreaName>Area 9</AreaName>
<AreaType>4</AreaType>
<AccessMap></AccessMap>
<AccessMapName></AccessMapName>
<AreaPos_X>104.91</AreaPos_X>
<AreaPos_X2>119.50</AreaPos_X2>
<AreaPos_Y>36.09</AreaPos_Y>
<AreaPos_Y2>48.16</AreaPos_Y2>
<AreaExpansion>
</AreaExpansion>
</Area>
<Area id="aUid11">
<AreaUID>11</AreaUID>
<AreaName>Area 10</AreaName>
<AreaType>4</AreaType>
<AccessMap></AccessMap>
<AccessMapName></AccessMapName>
<AreaPos_X>120.34</AreaPos_X>
<AreaPos_X2>135.13</AreaPos_X2>
<AreaPos_Y>49.63</AreaPos_Y>
<AreaPos_Y2>56.41</AreaPos_Y2>
<AreaExpansion>
</AreaExpansion>
</Area>
<Area id="aUid12">
<AreaUID>12</AreaUID>
<AreaName>Area 11</AreaName>
<AreaType>4</AreaType>
<AccessMap></AccessMap>
<AccessMapName></AccessMapName>
<AreaPos_X>73.50</AreaPos_X>
<AreaPos_X2>93.97</AreaPos_X2>
<AreaPos_Y>33.06</AreaPos_Y>
<AreaPos_Y2>52.03</AreaPos_Y2>
<AreaExpansion>
</AreaExpansion>
</Area>
<Area id="aUid15">
<AreaUID>15</AreaUID>
<AreaName>보물상자00</AreaName>
<AreaType>13</AreaType>
<AccessMap></AccessMap>
<AccessMapName></AccessMapName>
<AreaPos_X>117.81</AreaPos_X>
<AreaPos_X2>119.75</AreaPos_X2>
<AreaPos_Y>61.19</AreaPos_Y>
<AreaPos_Y2>62.44</AreaPos_Y2>
<AreaExpansion>
</AreaExpansion>
</Area>
<Area id="aUid16">
<AreaUID>16</AreaUID>
<AreaName>보물상자01</AreaName>
<AreaType>13</AreaType>
<AccessMap></AccessMap>
<AccessMapName></AccessMapName>
<AreaPos_X>39.09</AreaPos_X>
<AreaPos_X2>40.75</AreaPos_X2>
<AreaPos_Y>63.41</AreaPos_Y>
<AreaPos_Y2>64.44</AreaPos_Y2>
<AreaExpansion>
</AreaExpansion>
</Area>
<Area id="aUid17">
<AreaUID>17</AreaUID>
<AreaName>보물상자02</AreaName>
<AreaType>13</AreaType>
<AccessMap></AccessMap>
<AccessMapName></AccessMapName>
<AreaPos_X>83.53</AreaPos_X>
<AreaPos_X2>85.69</AreaPos_X2>
<AreaPos_Y>49.53</AreaPos_Y>
<AreaPos_Y2>50.53</AreaPos_Y2>
<AreaExpansion>
</AreaExpansion>
</Area>
<Area id="aUid18">
<AreaUID>18</AreaUID>
<AreaName>보물상자03</AreaName>
<AreaType>13</AreaType>
<AccessMap></AccessMap>
<AccessMapName></AccessMapName>
<AreaPos_X>39.59</AreaPos_X>
<AreaPos_X2>40.81</AreaPos_X2>
<AreaPos_Y>20.59</AreaPos_Y>
<AreaPos_Y2>21.59</AreaPos_Y2>
<AreaExpansion>
</AreaExpansion>
</Area>
<Area id="aUid19">
<AreaUID>19</AreaUID>
<AreaName>보물상자04</AreaName>
<AreaType>13</AreaType>
<AccessMap></AccessMap>
<AccessMapName></AccessMapName>
<AreaPos_X>110.22</AreaPos_X>
<AreaPos_X2>112.25</AreaPos_X2>
<AreaPos_Y>25.59</AreaPos_Y>
<AreaPos_Y2>26.56</AreaPos_Y2>
<AreaExpansion>
</AreaExpansion>
</Area>
<Area id="aUid20">
<AreaUID>20</AreaUID>
<AreaName>보물상자05</AreaName>
<AreaType>13</AreaType>
<AccessMap></AccessMap>
<AccessMapName></AccessMapName>
<AreaPos_X>84.00</AreaPos_X>
<AreaPos_X2>85.22</AreaPos_X2>
<AreaPos_Y>34.41</AreaPos_Y>
<AreaPos_Y2>35.38</AreaPos_Y2>
<AreaExpansion>
</AreaExpansion>
</Area>
</AreaData>
</MapData>
